Workbook

Sheet Read Me
A1: Pakistan AI Policy Monitor
A2: Evidence Register and Coverage Log | 18 August–3 September 2026 (UTC)
A3: Search cutoff: 2026-09-03 04:15 UTC | Evidence and lifecycle status should be rechecked before any later reuse.
A5: Interpretation boundary
A6: Comprehensive with respect to the supplied files and documented verification searches; not proof that every relevant public event was captured.
A8: Temporal caveat — The supplied corpus contains 14 briefing units against a nominal 1,440 runs for exactly 15 days at a 15-minute cadence. Negative findings are therefore bounded to the supplied files and documented searches; missing intervals are never imputed.
A11: Formula-driven control totals | G11: Coverage controls
A12: Control | B12: Live value | C12: Unit | D12: Expected | E12: Reconciliation | G12: Metric | H12: Live value | I12: Interpretation
A13: Evidence register rows | B13: =COUNTA('Evidence Register'!$A$5:$A$56) -> 52 | C13: records | D13: 52 | E13: =IF(B13=D13,"PASS","CHECK") -> PASS | G13: Nominal expected runs | H13: ='Coverage & Gaps'!$B$6 -> 1440 | I13: Exactly 15 days × 24 hours × 4 runs/hour
A14: In-period / verification-discovered | B14: =COUNTIF('Evidence Register'!$A$5:$A$56,"EVT-*") -> 36 | C14: records | D14: 36 | E14: =IF(B14=D14,"PASS","CHECK") -> PASS | G14: Observed briefing units | H14: ='Coverage & Gaps'!$B$7 -> 14 | I14: Normalized supplied briefing units
A15: Baseline / context | B15: =COUNTIF('Evidence Register'!$A$5:$A$56,"BASE-*") -> 16 | C15: records | D15: 16 | E15: =IF(B15=D15,"PASS","CHECK") -> PASS | G15: Nominal missing runs | H15: ='Coverage & Gaps'!$B$8 -> 1426 | I15: Expected minus observed
A16: Baseline carry-in | B16: =COUNTIFS('Evidence Register'!$A$5:$A$56,"BASE-*",'Evidence Register'!$Z$5:$Z$56,"BASELINE_CARRY_IN") -> 13 | C16: records | D16: 13 | E16: =IF(B16=D16,"PASS","CHECK") -> PASS | G16: Observed share | H16: ='Coverage & Gaps'!$B$9 -> 0.0097222222 | I16: Observed divided by nominal expected
A17: Baseline contradicted / unresolved | B17: =COUNTIFS('Evidence Register'!$A$5:$A$56,"BASE-*",'Evidence Register'!$Z$5:$Z$56,"CONTRADICTED_OR_UNRESOLVED") -> 3 | C17: records | D17: 3 | E17: =IF(B17=D17,"PASS","CHECK") -> PASS | G17: Strict-window share | H17: ='Coverage & Gaps'!$B$12 -> 0.0098024254 | I17: Strict observed minutes divided by observed span
A18: Sources | B18: =COUNTA(Sources!$A$5:$A$115) -> 111 | C18: records | D18: 111 | E18: =IF(B18=D18,"PASS","CHECK") -> PASS | G18: Search cutoff | H18: 2026-09-03T04:15:00Z | I18: Current-source verification boundary
A19: Briefing units | B19: =COUNTA('Briefing Units'!$A$5:$A$18) -> 14 | C19: units | D19: 14 | E19: =IF(B19=D19,"PASS","CHECK") -> PASS
A20: Exclusions | B20: =COUNTA(Exclusions!$A$5:$A$17) -> 13 | C20: items | D20: 13 | E20: =IF(B20=D20,"PASS","CHECK") -> PASS
A21: Watch items | B21: =COUNTA(Watchlist!$A$5:$A$18) -> 14 | C21: items | D21: 14 | E21: =IF(B21=D21,"PASS","CHECK") -> PASS
A22: High confidence | B22: =COUNTIF('Evidence Register'!$V$5:$V$56,"High") -> 32 | C22: records | D22: 32 | E22: =IF(B22=D22,"PASS","CHECK") -> PASS
A23: Medium confidence | B23: =COUNTIF('Evidence Register'!$V$5:$V$56,"Medium") -> 16 | C23: records | D23: 16 | E23: =IF(B23=D23,"PASS","CHECK") -> PASS
A24: Low confidence | B24: =COUNTIF('Evidence Register'!$V$5:$V$56,"Low") -> 4 | C24: records | D24: 4 | E24: =IF(B24=D24,"PASS","CHECK") -> PASS
A27: Evidence model and source hierarchy
A28: Layer | B28: Rule | C28: Why it matters | G28: Priority | H28: Source class | I28: Use
A29: Verified facts | B29: State only what an accessible record directly supports. | C29: Prevents announcement language from becoming implementation evidence. | G29: 1 | H29: Primary law, gazette, regulator, procurement register | I29: Lifecycle and operative-text conclusions
A30: Source claims | B30: Attribute unverified operational, scale, or outcome claims. | C30: Preserves what institutions said without adopting it as fact. | G30: 2 | H30: Official ministry, authority, institution, company | I30: Event facts and attributed claims
A31: Interpretation | B31: Separate analytical synthesis from sourced fact. | C31: Makes reasoning auditable and contestable. | G31: 3 | H31: Independent reporting | I31: Corroboration, context, and contested details
A32: Forward implications | B32: Express future-facing consequences as bounded scenarios. | C32: Avoids converting plausible pathways into forecasts. | G32: 4 | H32: Briefing corpus | I32: Discovery provenance only; never independent corroboration
A33: Lifecycle | B33: Classify proposal, consultation, approval, award, signing, delivery, and operation separately. | C33: Prevents stage inflation.
A34: Conflict | B34: Retain both dated versions and identify mutable-source limits. | C34: Preserves the WHO 24-Aug capture versus 28-Aug live-page discrepancy.
A37: Workbook navigation
A38: Evidence Register | B38: 52 distinct event/baseline records with lifecycle, confidence, facts, claims, analysis, implications, and source URLs.
A39: Coverage & Gaps | B39: Cadence controls, normalized observed span, and all 13 inter-briefing gaps.
A40: Exclusions | B40: Every out-of-scope, duplicate, or unsupported item and its disposition.
A41: Briefing Units | B41: B001–B014 source provenance, normalized UTC/PKT windows, timing issues, and SHA-256 hashes.
A42: Sources | B42: S001–S111 source register with plain-text URLs and limitations.
A43: Watchlist | B43: W001–W014 future triggers and verification tasks.
A44: File Inventory | B44: All 13 received top-level files, readability, metadata, hashes, and inclusion decisions.
A45: Methodology | B45: Reproducibility chain, source hierarchy, lifecycle rules, confidence rubric, and refresh protocol.

Sheet Evidence Register
A1: Evidence Register
A2: One row per distinct event or retained baseline/context record. Facts, claims, analysis, implications, uncertainty, and lifecycle remain separate.
A4: Event ID | B4: Normalized Event Title | C4: Category | D4: Institution | E4: Geography | F4: Event Date | G4: Publication Date | H4: First Detected | I4: Last Updated | J4: Briefing File References | K4: Primary Source IDs | L4: Primary Source URLs | M4: Corroborating Source IDs | N4: Corroborating Source URLs | O4: Status | P4: Verified Facts | Q4: Source Claims | R4: What Changed | S4: Significance | T4: Analytical Interpretation | U4: Forward Implications | V4: Confidence | W4: Confidence Reason | X4: Unresolved Issues | Y4: Inclusion Decision | Z4: Lifecycle
A5: EVT-GOOG-20260818-OFFICE | B5: Google Pakistan office inauguration claim | C5: GOOGLE_CORPORATE_PRESENCE | D5: Google; Government of Pakistan | E5: Islamabad / national | F5: 46252 | G5: 2026-08-18; retrospective PDA item 2026-09-01 | H5: 2026-08-18T19:38Z (B001) | I5: 2026-09-03T02:21Z (B014) | J5: B001; B002; B003; B004; B005; B006; B007; B008; B009; B010; B011; B012; B013; B014 | K5: S074; S075; S081; S082; S083 | L5: https://pid.gov.pk/site/press_detail/33638 | https://pda.gov.pk/press-details.php?id=google-opens-office-in-pakistan | https://about.google/company-info/locations/ | https://cloud.google.com/about/locations | https://datacenters.google/locations/ | M5: S076; S084 | N5: https://www.dawn.com/news/2023681 | https://www.google.com/about/careers/applications/jobs/results?location=Pakistan | O5: government/company-reported inauguration; physical operation unverified | P5: A plaque-marking ceremony involving the prime minister and a Google delegation occurred at Prime Minister House on 18 August. Google’s current canonical office, Cloud-region and owned-data-centre directories showed no Pakistan listing at the verification cutoff. | Q5: Pakistani authorities and contemporaneous reporting called the event the opening or establishment of Google’s first local office. | R5: The reporting period added a high-level ceremony and public local-office claim, but later checks did not supply premises-level evidence. | S5: The distinction affects how investors, regulators and users should understand local accountability, staffing, tax presence, and data-hosting implications. | T5: Evidence supports an announced/local corporate presence, not a confidently verified staffed operational office at a disclosed physical location. | U5: Verify street address, premises operator, occupancy, employing entity, staff, mandate and any local processing/hosting before upgrading status. | V5: Medium | W5: High confidence in the ceremony and directory state; insufficient evidence for physical operation, location and timing of an operating office. | X5: Physical address; office type; occupancy; headcount; employing entity; mandate; investment; data processing; hosting jurisdiction. | Y5: include with explicit qualification | Z5: IN_SPAN_DEVELOPMENT
A6: EVT-GOOG-20260821-MOU | B6: Government of Pakistan–Google framework MoU and programme announcements | C6: FUNDING_INVESTMENT_PARTNERSHIP | D6: Google; MoITT; Government of Pakistan | E6: Islamabad / national | F6: 46255 | G6: 2026-08-21 and 2026-08-24 | H6: 2026-08-21T15:05Z (B003) | I6: 2026-09-03T02:21Z (B014) | J6: B003; B005; B006; B010; B014 | K6: S077 | L6: https://pid.gov.pk/site/press_detail/33684 | M6: S078; S079 | N6: https://www.moib.gov.pk/News/66341 | https://pid.gov.pk/site/press_detail/33645 | O6: signed/announced framework MoU; delivery not evidenced | P6: PID records a framework MoU dated 21 August and programme targets including 150,000 Career Certificates in 2026 and exploration of one-year student access to Google AI Plus/Gemini and NotebookLM, an Islamabad AI centre, and FBR support. | Q6: Government releases report earlier programme outputs and prospective skills, education, SME, agriculture, payments, app and gaming initiatives. | R6: A cooperation framework and numeric training target entered the record; no budget release, beneficiary completion, centre opening or system acceptance was found. | S6: The package could shape workforce supply and public-sector vendor relationships, but implementation terms determine actual value and data-governance exposure. | T6: This is a programme-intent milestone, not realized investment or delivered capacity. | U6: Seek the signed instrument, workplan, budgets, selection rules, data flows, hosting terms and output audits. | V6: Medium | W6: Strong official evidence of the announcement; primary instrument and delivery evidence unavailable. | X6: Signed text; budget; beneficiary selection; centre site/operator/timeline; data flows; local hosting; independent outcome audit. | Y6: include | Z6: IN_SPAN_DEVELOPMENT
A7: EVT-REG-20260821-PVARA | B7: PVARA virtual-asset service regulations notified | C7: DATA_PROTECTION_GOVERNANCE | D7: Pakistan Virtual Assets Regulatory Authority | E7: Federal / Pakistan | F7: 46255 | G7: 46255 | H7: 2026-08-22T15:05Z (B004) | I7: 2026-08-31T14:55Z (B012) | J7: B004; B005; B006; B007; B008; B011; B012 | K7: S018; S019; S020 | L7: https://pvara.gov.pk/documents/Pakistan%20Virtual%20Asset%20Services%20Regulations,%202026%20-%20Notified%2021%20August%202026.pdf | https://pvara.gov.pk/documents/Pakistan%20Virtual%20Asset%20Services%20Activity%20Specific%20Regulations,%202026%20-%20Notified%2021%20August%202026.pdf | https://pvara.gov.pk/licensing | M7: S017; S021 | N7: https://pvara.gov.pk/regulations | https://radio.gov.pk/22-08-2026/pakistan-introduces-transparent-regulatory-system-for-digital-economy | O7: notified and effective regulations | P7: S.R.O. 1419(I)/2026 and S.R.O. 1420(I)/2026 were notified on 21 August and SRO 1419 states commencement on Gazette notification unless a later date is specified. Verified duties include technology/cyber controls, cloud and cross-border safeguards, incident reporting and personal-data programmes. General and activity-specific records are retained at least seven years; material cyber/BCDR notice is due within 24 hours, an interim update within five working days, final report within 30 calendar days, and personal-data incident notice within 72 hours. | Q7: The summary page states a minimum ten-year record-keeping rule, but the operative regulations use seven years generally; ten years applies in a narrower unclaimed-wallet/assets context. | R7: The framework moved from enabling legislation/guidance to two operative sector regulations. | S7: VASPs now face concrete licensing, governance, cloud, cyber, algorithm and personal-data obligations with reportable deadlines. | T7: This was the clearest binding digital-regulatory development in the supplied monitoring span. | U7: Track transitional applications, licensing decisions, supervisory guidance, enforcement and cloud/cross-border implementation. | V7: High | W7: Operative Gazette texts were opened and checked directly. | X7: First licences/NOCs; enforcement; treatment of specific cloud architectures; publication of reasoned decisions. | Y7: include | Z7: IN_SPAN_DEVELOPMENT
A8: EVT-CYB-20260824-PKCERT16 | B8: PKCERT publishes Advisory 16 on synchronized passkeys | C8: CYBERSECURITY | D8: PKCERT | E8: Federal / Pakistan | F8: 2026-08-24 (identifier and PDF metadata) | G8: 2026-08-24 (metadata-supported) | H8: 2026-08-24T19:25Z (B006) | I8: 2026-09-03T02:21Z (B014) | J8: B006; B007; B008; B009; B010; B011; B012; B013; B014 | K8: S022; S023 | L8: https://pkcert.gov.pk/advisories.asp | https://pkcert.gov.pk/advisory/26/16.pdf | O8: published advisory | P8: The live register lists Advisory 16, NCA-16.240826, concerning malware targeting synchronized passkeys on compromised Windows systems. | R8: It superseded the corpus’s prior observation that Advisory 15 topped the register. | S8: It is an operational cyber-risk publication, not a new law or incident disclosure. | T8: Useful threat guidance, but no evidence of a Pakistan-specific breach or mandated remediation was located. | U8: Track agency adoption and any incident reporting. | V8: High | W8: Official PDF and register; date is metadata-supported but exact release time is unavailable. | X8: Exact publication timestamp; implementation by covered entities. | Y8: include | Z8: IN_SPAN_DEVELOPMENT
A9: EVT-CYB-20260824-PKCERT17 | B9: PKCERT publishes Advisory 17 on an Acrobat extension exposure | C9: CYBERSECURITY | D9: PKCERT | E9: Federal / Pakistan | F9: 2026-08-24 (identifier and PDF metadata) | G9: 2026-08-24 (metadata-supported) | H9: 2026-08-24T19:25Z (B006) | I9: 2026-09-03T02:21Z (B014) | J9: B006; B007; B008; B009; B010; B011; B012; B013; B014 | K9: S022; S024 | L9: https://pkcert.gov.pk/advisories.asp | https://pkcert.gov.pk/advisory/26/17.pdf | O9: published advisory | P9: The live register lists Advisory 17, NCA-17.240826, on an Adobe Acrobat Chrome extension vulnerability exposing WhatsApp Web sessions. | R9: The advisory became the top visible 2026 listing by the B006 cutoff. | S9: The notice expands official threat guidance relevant to organizational browsers and messaging sessions. | T9: It should not be treated as evidence of a Pakistan-specific compromise. | U9: Monitor follow-on directives or incident notices. | V9: High | W9: Official PDF and register; exact release time is unavailable. | X9: Exact publication timestamp; affected-estate evidence; implementation uptake. | Y9: include | Z9: IN_SPAN_DEVELOPMENT
A10: EVT-TEL-20260828-AMENDMENT-WITHDRAWN | B10: Pakistan Telecommunication amendment bill withdrawn | C10: PLATFORM_TELECOM | D10: Parliament; MoITT | E10: Federal / Islamabad | F10: 46262 | G10: 46262 | H10: 2026-08-28T14:52Z (B009) | I10: 2026-08-29T14:38Z (B010) | J10: B009; B010 | K10: S025; S026 | L10: https://pid.gov.pk/site/press_detail/33741 | https://www.senate.gov.pk/en/gbna.php?catid=186&cattitle=Bills&leftcatid=279&subcatid=276 | O10: withdrawn; replacement announced but not introduced | P10: The Senate register records the bill withdrawn in the House on 28 August. MoITT said it intended a fresh bill retaining the proposal’s essence. | R10: The pending bill ceased to advance; the replacement remained executive intent at cutoff. | S10: No operative telecom-law change arose from the withdrawn text, reducing immediate compliance impact but preserving policy uncertainty. | T10: Treat future legislation as a new event requiring a new text and parliamentary lifecycle. | U10: Watch for introduction, referral, amendments, passage, assent, Gazette and commencement. | V10: High | W10: Official executive and parliamentary records align on withdrawal. | X10: Successor text, title, introduction date and operative provisions. | Y10: include | Z10: IN_SPAN_DEVELOPMENT
A11: EVT-KP-20260821-DIGITAL-PAYMENTS | B11: KP Digital Payments Bill passage claim conflicts with official tracker | C11: DIGITAL_IDENTITY_DPI | D11: Khyber Pakhtunkhwa Assembly | E11: Khyber Pakhtunkhwa / Peshawar | F11: 2026-08-21 (reported) | G11: 46256 | H11: 2026-08-22T15:05Z (B004) | I11: 2026-08-22T15:05Z (B004) | J11: B004 | K11: S027 | L11: https://www.pakp.gov.pk/bill/the-khyber-pakhtunkhwa-promotion-of-digital-payments-bill-2026/ | M11: S028 | N11: https://tribune.com.pk/story/2625229/k-p-assembly-approves-digital-payments-bill | O11: officially referred to committee; reported passage unverified | P11: The official tracker currently shows the bill introduced on 6 April 2026 and referred to Standing Committee No. 10. | Q11: A news headline says the Assembly approved the bill on 21 August, while the article body also describes it as introduced. | R11: A reported passage claim appeared, but authoritative disposition did not confirm it. | S11: Misclassifying the bill as enacted would falsely create payment obligations and a rulemaking clock. | T11: No Act, assent, Gazette or commencement is verified. | U11: Recheck committee report, passed-bills register, assent and Gazette. | V11: High | W11: High on current official status; low on reported passage. | X11: Authoritative 21 August proceedings; final text; vote; assent; Gazette; commencement; rulemaking. | Y11: include as disputed status | Z11: CONTRADICTED_OR_UNRESOLVED
A12: EVT-KP-20260827-VIRTUAL-WORKPLACE | B12: KP committee recommends digital-workplace harassment amendments | C12: DATA_PROTECTION_GOVERNANCE | D12: KP Assembly Standing Committee | E12: Khyber Pakhtunkhwa / Peshawar | F12: 46261 | G12: 46261 | H12: 2026-08-27T14:06Z (B008) | I12: 2026-08-27T14:06Z (B008) | J12: B008 | K12: S029 | L12: https://dgipr.kp.gov.pk/sc-27-8-26/ | O12: committee recommendation; not enacted | P12: A provincial committee considered and recommended amendments extending workplace-protection concepts to digital, virtual and remote environments and electronic evidence. | R12: The proposal advanced at committee level only. | S12: It signals recognition of digitally mediated workplace harms but does not yet alter legal duties. | T12: Evidence, privacy, jurisdiction and platform-process rules remain central design questions. | U12: Track bill text, Assembly vote, assent, Gazette and rules. | V12: High | W12: Official provincial release is clear about committee stage. | X12: Amendment text; evidentiary safeguards; vote; assent; commencement. | Y12: include | Z12: IN_SPAN_DEVELOPMENT
A13: EVT-SECP-20260827-C19 | B13: SECP Circular No. 19 of 2026 on investor onboarding | C13: DATA_PROTECTION_GOVERNANCE | D13: Securities and Exchange Commission of Pakistan | E13: Federal / Islamabad | F13: issued 2026-08-25; posted 2026-08-27 | G13: 2026-08-27; press coverage 2026-08-28 | H13: 2026-08-27T14:06Z (B008) | I13: 2026-09-03T04:15Z (verification) | J13: B008 | K13: S101; S102 | L13: https://www.secp.gov.pk/document/circular-no-19-of-2026-consolidated-framework-for-investor-onboarding-secp-regulated-persons/ | https://www.secp.gov.pk/laws/circulars/ | M13: S103; S104 | N13: https://www.dawn.com/news/2025777 | https://www.brecorder.com/news/40436941 | O13: final issued circular; commencement date unstated; three-month transition | P13: Circular 19/2026 was issued on 25 August and posted on the official register on 27 August. It repeals Circular 6/2023 while preserving prior actions. For complete individual-customer documents, the maximum accept/decline period is one working day for Sehl/Sahulat accounts and two working days for Normal Accounts; deficiencies must be communicated within the same period and rejection reasons supplied in writing. Firms have three months to align forms and establish portal connectivity, subject to extension. | Q13: Government reporting linked the reform to a 2.5 million investor-base objective; that is policy context, not an intermediary obligation. | R13: A final onboarding framework replaced the 2023 circular and introduced measurable processing deadlines and transition requirements. | S13: The circular converts a general digitisation agenda into binding process obligations for specified securities and financial-market intermediaries. | T13: Do not infer an effective date, extend the individual-account turnaround to juridical applicants, or treat issuance as proof of intermediary compliance. | U13: Track clarification of the immediate-connectivity language, the transition end point, extensions, portal readiness, rejection data and supervisory compliance. | V13: High | W13: Official register and eight-page circular were inspected directly; dates and provisions were cross-checked against two reputable reports. | X13: Express effective date; juridical-person turnaround; reconciliation of immediate connectivity with the transition; extensions; operational compliance. | Y13: include | Z13: IN_SPAN_DEVELOPMENT
A14: EVT-PLAT-20260901-PUNJAB-U16 | B14: Punjab Assembly reportedly passes under-16 social-media resolution | C14: PLATFORM_TELECOM | D14: Punjab Assembly | E14: Punjab / Lahore | F14: 46266 | G14: 46266 | H14: 2026-09-01T16:51Z (B013) | I14: 2026-09-01T16:51Z (B013) | J14: B013 | M14: S032 | N14: https://humenglish.com/latest/punjab-assembly-passes-resolution-to-ban-social-media-accounts-for-under-16s/ | O14: reported non-binding resolution; official text unavailable | P14: A news report says the Assembly adopted a resolution urging restrictions and age verification for under-16 accounts. | R14: A provincial political recommendation entered the debate; no enacted platform duty followed. | S14: Age assurance could affect biometric processing, exclusion, appeals and federal-provincial competence. | T14: The resolution is agenda-setting, not legislation or a PTA rule. | U14: Obtain the official resolution and track any bill, PTA instrument or implementation design. | V14: Low | W14: One credible report; no official resolution text located. | X14: Official text; legal route; verification method; retention; redress; federal authority. | Y14: include with qualification | Z14: IN_SPAN_DEVELOPMENT
A15: EVT-PLAT-20260831-IHC-U16 | B15: IHC seeks replies in under-16 age-verification petition | C15: PLATFORM_TELECOM | D15: Islamabad High Court | E15: Islamabad / federal respondents | F15: 46265 | G15: 2026-08-31 and 2026-09-01 | H15: 2026-09-01T16:51Z (B013) | I15: 2026-09-03T02:21Z (B014) | J15: B013; B014 | M15: S033; S034 | N15: https://www.dawn.com/news/2026379 | https://www.brecorder.com/news/40437291/social-media-age-verification-ihc-direct-authorities-to-submit-reply | O15: procedural notice/reply stage; no final judgment | P15: Two news reports describe notices and a request for replies within 15 days in a petition concerning age verification. | R15: The petition moved into a response stage, not final adjudication. | S15: A future order could shape platform age assurance, regulator duties and privacy safeguards. | T15: No substantive rule or obligation should be inferred from notice issuance. | U15: Retrieve the authenticated order, respondent filings and later disposition. | V15: Medium | W15: Two reputable reports align; court order itself was not located. | X15: Authenticated order; petition text; respondents; filings; final disposition. | Y15: include | Z15: IN_SPAN_DEVELOPMENT
A16: EVT-ID-20260901-NADRA-FBISE | B16: NADRA–FBISE student identity and certificate integration agreement | C16: DIGITAL_IDENTITY_DPI | D16: NADRA; Federal Board of Intermediate and Secondary Education | E16: Islamabad / national | F16: 46266 | G16: 46266 | H16: 2026-09-01T16:51Z (B013) | I16: 2026-09-01T16:51Z (B013) | J16: B013 | K16: S035 | L16: https://www.app.com.pk/national/nadra-fbise-sign-agreement-to-integrate-student-registration-educational-certificates-system/ | O16: agreement signed; deployment not evidenced | P16: APP reports an agreement for mutual exchange of name, father’s name and date of birth, with a planned secure digital wallet for certificates. | R16: The agencies formalized an integration intention; no production milestone or data-protection instrument was published. | S16: The project involves student/child data, identity matching and credential recovery, making legal basis and safeguards consequential. | T16: A signed agreement is not proof that a secure wallet or live data exchange is operating. | U16: Seek agreement text, data-flow diagrams, access controls, retention, correction, breach response, audits and launch acceptance. | V16: Medium | W16: Official news-agency report; underlying instrument and system evidence unavailable. | X16: Agreement text; legal basis; production status; minimisation; access/logging; retention; child safeguards; redress. | Y16: include | Z16: IN_SPAN_DEVELOPMENT
A17: EVT-PROC-20260818-31-AI-HUBS | B17: National AI Hubs procurement advertised and closed | C17: PROCUREMENT_PROGRAM_DELIVERY | D17: MoITT — Digital Emerging Technologies Wing | E17: Islamabad / national | F17: 2026-08-18 to 2026-08-31 | G17: 46252 | H17: 2026-08-18T19:38Z (B001) | I17: 2026-09-03T02:21Z (B014) | J17: B001; B002; B003; B004; B005; B006; B007; B008; B009; B010; B011; B012; B013; B014 | K17: S036; S037 | L17: https://epms.ppra.gov.pk/public/tenders/tender-details/TS0000010287E | https://epads.gov.pk/opportunities/federal/procurements/71677 | O17: closed for bids; pre-evaluation/pre-award | P17: The consultancy tender was advertised 18 August and the current record shows closing at 14:00 PKT and opening at 14:30 on 31 August, single-stage two-envelope, PKR 3 million bid security and 180-day validity. No evaluation or award was visible. | Q17: The tender history retains an inconsistent 19 August closing entry. | R17: The procurement moved from open to closed, but not to evaluated, awarded, contracted or delivered. | S17: The tender is a potential delivery vehicle for the National AI Policy, but no hub, site, budget expenditure or service exists merely because bidding closed. | T17: Procurement momentum remains upstream of implementation. | U17: Track opening record, bidders, technical evaluation, grievance, award, contract, sites, equipment and acceptance. | V17: High | W17: Official procurement records; internal history conflict preserved. | X17: Bidder/opening record; evaluation; award; contract; locations; equipment; safeguards; acceptance. | Y17: include | Z17: IN_SPAN_DEVELOPMENT
A18: EVT-PROC-20260819-MOITT-TRAINING | B18: MoITT AI capacity-building procurement reaches final evaluation | C18: WORKFORCE_RESEARCH_EDUCATION | D18: MoITT | E18: Federal / online | F18: 46253 | G18: 46253 | H18: 2026-08-20T14:50Z (B002) | I18: 2026-08-20T14:50Z (B002) | J18: B002 | K18: S038; S039 | L18: https://epms.ppra.gov.pk/public/tenders/tender-details/TS0000006913E | https://epms.ppra.gov.pk/public/evaluations?page=7 | O18: final evaluation; not awarded | P18: The procurement targets 20,000 online trainings; the evaluation listed 17 bids and NCBMS as lowest. | R18: Bid comparison reached final-evaluation stage. | S18: Potential workforce scale is material, but bidder ranking is not delivered training. | T18: Outcome claims should wait for award, contract, enrolment, completion and assessment evidence. | U18: Track award, contract value, curriculum, enrolment, completions and independent learning outcomes. | V18: High | W18: Official procurement record; stage distinction is clear. | X18: Award; contract; value; provider obligations; delivery; completion and outcome evidence. | Y18: include | Z18: IN_SPAN_DEVELOPMENT
A19: EVT-PROC-20260821-28-NAVTTC-AI-SERVICES | B19: NAVTTC AI-enabled services procurement advances from technical to final evaluation | C19: PROCUREMENT_PROGRAM_DELIVERY | D19: NAVTTC | E19: Federal / Pakistan | F19: 2026-08-21 and 2026-08-28 | G19: 2026-08-21 and 2026-08-28 | H19: 2026-08-21T15:05Z (B003) | I19: 2026-08-28T14:52Z (B009) | J19: B003; B004; B008; B009 | K19: S040; S041; S042 | L19: https://epms.ppra.gov.pk/public/tenders/tender-details/TS0000010237E | https://epms.ppra.gov.pk/public/evaluations?page=1 | https://epms.ppra.gov.pk/public/evaluations?page=4 | O19: final evaluation; not awarded | P19: A technical evaluation on 21 August covered six bids; a final evaluation dated 28 August listed Mercurial Minds as lowest evaluated bidder. | R19: This was a genuine procurement-stage update, not duplicate coverage. | S19: It narrows the likely supplier but does not establish contract execution or an operational AI-enabled service. | T19: Procurement registers should be read as a lifecycle, not as binary project completion. | U19: Track award, contract, scope, data safeguards, deployment, tests and acceptance. | V19: High | W19: Official evaluation records at two stages. | X19: Award; price; signed contract; implementation scope; data governance; acceptance. | Y19: include | Z19: IN_SPAN_DEVELOPMENT
A20: EVT-PROC-20260827-PTA-DIRBS | B20: PTA AI-powered DIRBS tender closes | C20: AI_GOVERNANCE | D20: Pakistan Telecommunication Authority | E20: Federal / Pakistan | F20: 46261 | G20: 46244 | H20: 2026-08-18T19:38Z (B001) | I20: 2026-08-27T14:06Z (B008) | J20: B001; B002; B003; B004; B005; B006; B007; B008 | K20: S043; S044 | L20: https://epms.ppra.gov.pk/public/tenders/tender-details/TS0000011207E | https://epads.gov.pk/federal/annual-plan/procurement/2473/7564/2026-27 | O20: closed tender; no evaluation or award | P20: The consultancy tender advertised 10 August closed at 11:00 PKT on 27 August under a single-stage one-envelope procedure with 120-day validity. No result was visible. | Q20: Annual-plan and tender metadata do not fully align. | R20: Bidding closed; system design, vendor selection and deployment remain unverified. | S20: AI use in device-registration enforcement could affect lawful device access, false positives and procedural rights. | T20: Governance questions are material before procurement reaches operation. | U20: Demand legal basis, data inputs, testing, accuracy thresholds, human review, auditability, retention and appeals. | V20: High | W20: Official tender record for closure; technical and safeguards evidence absent. | X20: Metadata reconciliation; evaluation; award; architecture; accuracy; human review; retention; redress. | Y20: include | Z20: IN_SPAN_DEVELOPMENT
A21: EVT-PROC-20260820-NADRA-RACKS | B21: NADRA NDW racks, containment and PDU tender closes | C21: COMPUTE_CLOUD_DATACENTRE | D21: NADRA | E21: Federal / Pakistan | F21: 46254 | G21: 46232 | H21: 2026-08-20T14:50Z (B002) | I21: 2026-08-20T14:50Z (B002) | J21: B002 | K21: S045 | L21: https://epms.ppra.gov.pk/public/tenders/tender-details/TS0000010535E | O21: closed tender; pre-evaluation | P21: The tender for NDW racks, containment systems and rack PDUs closed 20 August at 11:00 PKT with PKR 580,000 bid security and 120-day validity. | R21: Bidding closed without a visible downstream result. | S21: The procurement is enabling physical infrastructure, not proof of expanded compute capacity or service resilience. | T21: Capacity should be counted only after delivery, testing and acceptance. | U21: Track evaluation, award, installation, commissioning and acceptance. | V21: High | W21: Official procurement record. | X21: Evaluation; award; value; delivery; commissioning; accepted capacity. | Y21: include | Z21: IN_SPAN_DEVELOPMENT
A22: EVT-PROC-20260820-NADRA-SWITCHES | B22: NADRA branch-switch and management-licence tender closes | C22: CONNECTIVITY_ENERGY_RESILIENCE | D22: NADRA | E22: Federal / Pakistan | F22: 46254 | G22: 2026 | H22: 2026-08-20T14:50Z (B002) | I22: 2026-08-20T14:50Z (B002) | J22: B002 | K22: S046 | L22: https://epms.ppra.gov.pk/public/tenders/tender-details/TS0000010591E | O22: closed tender; pre-evaluation | P22: The tender covered 237 Layer-2 switches, 30 PoE switches and 267 central-management licences; it closed 20 August at 11:00 PKT with PKR 600,000 bid security and 120-day validity. | R22: Bidding closed without a visible evaluation or award. | S22: It may improve branch-network manageability but is not AI compute or proven operational resilience. | T22: Keep networking inputs distinct from compute capacity. | U22: Track evaluation, award, rollout, security configuration and acceptance. | V22: High | W22: Official procurement record. | X22: Evaluation; award; delivery; deployment; security acceptance. | Y22: include | Z22: IN_SPAN_DEVELOPMENT
A23: EVT-PROC-20260828-WHO-BALOCHISTAN-GIS | B23: WHO GIS-enabled EPI microplanning and NEIR integration RFP updated | C23: PROCUREMENT_PROGRAM_DELIVERY | D23: World Health Organization Pakistan | E23: Balochistan | F23: 2026-08-27 pre-bid meeting; deadline extended to 2026-09-06 | G23: 2026-08-24 in B006 capture; current page displays 2026-08-28 | H23: 2026-08-24T19:25Z (B006, earlier schedule observed) | I23: 2026-09-03 verification | J23: B006 | K23: S047 | L23: https://www.ungm.org/Public/Notice/310156 | O23: open RFP; deadline extended; pre-award | P23: B006 captured the notice on 24 August and transcribed its publication field as 24 August; the current mutable UNGM page instead displays publication on 28 August. The current page also records a 27 August 14:00 PKT pre-bid meeting and an extended deadline of 6 September 2026 at 11:00 PKT for GIS-enabled EPI microplanning and NEIR integration. | Q23: The observed publication date conflicts: 24 August in B006 versus 28 August on the current page. The page also retains superseded 24 and 31 August deadlines in its update history. | R23: The mutable record and schedule were revised; no award or implementation occurred in the period. | S23: The procurement involves geospatial and immunisation data, requiring careful access, retention, hosting and public-health governance. | T23: It is a live procurement signal, not a deployed health-data system. | U23: Track award, architecture, security, hosting, role-based access, retention and ethics controls. | V23: High | W23: Current international procurement record opened directly; version history preserved. | X23: Award; contract; data controller/processor roles; hosting; access; retention; ethics; production acceptance. | Y23: include | Z23: IN_SPAN_DEVELOPMENT
A24: EVT-TEL-20260827-JAZZ-5G | B24: Jazz reports reaching 1,000 live 5G sites | C24: PLATFORM_TELECOM | D24: Jazz | E24: Ten Pakistani cities | F24: 46261 | G24: 46261 | H24: 2026-08-28T14:52Z (B009) | I24: 2026-08-28T14:52Z (B009) | J24: B009 | K24: S048; S049 | L24: https://jazz.com.pk/media-center/detail/jazz-becomes-first-operator-to-reach-1000-5g-sites | https://jazz.com.pk/media-center/detail/jazz-secures-190-mhz-spectrum-to-accelerate-pakistans-5g-future | O24: company-reported operational footprint | P24: Jazz publicly reported 1,000 live 5G sites across ten cities, a target of 2,500 by end-2026, 190 MHz of spectrum and a prior US$1 billion commitment. | Q24: Operational-site and investment figures are company claims. | R24: The operator announced a footprint milestone during the reporting period. | S24: 5G reach influences edge connectivity and enterprise/cloud adoption, but site count does not establish coverage quality, affordability or realized capex. | T24: Treat the milestone as direct-company evidence pending independent coverage/QoS validation. | U24: Verify coverage maps, independent QoS, spectrum deployment and realized investment. | V24: Medium | W24: Direct company release; independent validation absent. | X24: Site definitions; geographic coverage; QoS; user access; realized capex. | Y24: include | Z24: IN_SPAN_DEVELOPMENT
A25: EVT-TEL-20260821-25-FAB-MONITORING | B25: FAB signs spectrum-monitoring equipment contract | C25: CONNECTIVITY_ENERGY_RESILIENCE | D25: Frequency Allocation Board; Rohde & Schwarz | E25: Islamabad / national | F25: 46255 | G25: 46259 | H25: 2026-08-29T14:38Z (B010) | I25: 2026-08-29T14:38Z (B010) | J25: B010 | K25: S050 | L25: https://epms.ppra.gov.pk/public/contracts/contract-details/PCN-3884318406 | O25: signed contract; commissioning unverified | P25: The contract record lists Rohde & Schwarz, PKR 196,308,167, two bids, three digital RF receivers, four sensor systems, training, one-year warranty and ten-year support; signed 21 August and published 25 August. | R25: The procurement reached signed-contract stage. | S25: It can strengthen spectrum oversight relevant to 5G reliability, but equipment is not operational until installed and accepted. | T25: This is stronger than an evaluation but weaker than commissioned capability. | U25: Track delivery, installation, training, commissioning, acceptance and utilisation. | V25: High | W25: Official contract record with vendor, value and scope. | X25: Delivery; installation sites; commissioning; acceptance; operational use. | Y25: include | Z25: IN_SPAN_DEVELOPMENT
A26: EVT-INF-20260821-SKY47-COMMERCE | B26: Commerce Ministry explores sovereign cloud and AI trade infrastructure with PDA and Sky47 | C26: COMPUTE_CLOUD_DATACENTRE | D26: Ministry of Commerce; PDA; Sky47 | E26: Federal / Pakistan | F26: 46255 | G26: 46255 | H26: 2026-09-01T16:51Z (B013, retrospective extraction) | I26: 2026-09-01T16:51Z (B013) | J26: B013 | K26: S051 | L26: https://pid.gov.pk/site/press_detail/33671 | O26: exploratory meeting / technical consultation | P26: The minister held separate meetings with PDA and Sky47 on data exchange, sovereign cloud, cybersecurity, disaster recovery, AI-enabled trade analysis and procurement reform; teams were directed to continue technical consultations and develop proposals. | Q26: Sky47 briefed the minister on existing infrastructure and expansion plans. | R26: A government-use discussion occurred; no contract, migration or activation was reported. | S26: The discussion identifies possible public-sector demand and governance questions around authorized data, procurement and domestic hosting. | T26: The 8.5 MW Karakoram-01 capacity belongs to a July baseline, not this meeting. | U26: Track approved architecture, procurement, data classification, cloud contracts, migration and acceptance. | V26: High | W26: Official release directly supports the meeting and forward-looking status. | X26: Proposal; contract; workloads; hosting; data-sharing controls; budget; acceptance. | Y26: include | Z26: IN_SPAN_DEVELOPMENT
A27: EVT-PART-20260827-RESECURITY-SKY47 | B27: Resecurity–Sky47 cybersecurity cooperation MoU announced | C27: FUNDING_INVESTMENT_PARTNERSHIP | D27: Resecurity; Sky47 | E27: Pakistan | F27: signing date and place unstated; first-party announcement 2026-08-27 | G27: 2026-08-27; advertorial 2026-08-29, modified 2026-08-31 | H27: 2026-08-29T14:38Z (B010) | I27: 2026-09-03T04:15Z (verification) | J27: B010 | K27: S086 | L27: https://www.linkedin.com/posts/sky47limited_sky47-resecurity-cybersecurity-activity-7498665122295517184-fA11 | M27: S087; S055 | N27: https://c-suite.exchange/sky47-and-resecurity-sign-mou-to-strengthen-cybersecurity-collaboration/ | https://www.dawn.com/news/2025965/resecurity-and-sky47-partner-to-enable-sovereign-cybersecurity-and-ai-infrastructure-in-pakistan | O27: signed exploratory MoU; no deployment or service contract | P27: Sky47 announced the signing of an MoU with Resecurity and said the parties will explore cooperation. The first-party announcement was posted on 27 August at approximately 13:58 PKT; neither it nor later reports states the physical signing date or place. | Q27: A Resecurity-supplied Dawn advertorial says the parties intend to explore secure deployment models for threat intelligence, fraud prevention, digital-risk monitoring, identity protection, AI-powered cybersecurity workloads and GPU-enabled infrastructure. | R27: A prospective cooperation framework was signed and announced; no customer, value, duration, workload, capacity or delivery date was disclosed. | S27: It indicates private demand for data residency and in-country hosting but does not quantify realized capacity. | T27: Treat the MoU as a verified relationship milestone, not as service delivery or proof of new AI/GPU capacity. | U27: Verify contracts, customers, data-processing terms, certifications, GPU inventory, deployment and exit obligations. | V27: High | W27: First-party announcement verifies the MoU and prospective language; delivery remains low-confidence and the signing date is unknown. | X27: Physical signing date/place; term; value; contract; customers; workloads; facility; GPUs; processing terms; certifications; deployment. | Y27: include | Z27: IN_SPAN_DEVELOPMENT
A28: EVT-RD-20260829-PSEB-NED | B28: PSEB–NED semiconductor education and research cluster contract signed | C28: WORKFORCE_RESEARCH_EDUCATION | D28: Pakistan Software Export Board; NED University | E28: Karachi / South Region | F28: 46263 | G28: 46263 | H28: 2026-08-29T14:38Z (B010) | I28: 2026-08-29T14:38Z (B010) | J28: B010 | K28: S088; S089; S090 | L28: https://pid.gov.pk/site/press_detail/33749 | https://techdestination.com/wp-content/uploads/2025/09/Request-for-Proposal-NSHRDP-SERC-Procurement-2.51.pdf | https://pid.gov.pk/site/press_detail/32338 | M28: S056; S057 | N28: https://www.moitt.gov.pk/NewsDetail/MTJmOTg2OGQtOTNlYi00MDZjLTk0MDktNGRiMmQzMTEzYTdm | https://www.neduet.edu.pk/content/events | O28: contract signed / lead-university designation; commencement and disbursement unverified | P28: PID reports a contract naming NED the South Region lead university and completing three regional SERC agreements. It reports 270 students across all regions and a target exceeding 7,200 professionals by 2030. The procurement framework requires inspection and a commencement certificate before academic activity and disbursement. | Q28: The ministry says INSPIRE moves into full-scale implementation. The PKR 4.844 billion figure cited elsewhere is the entire National Semiconductor Human Resource Development Program budget, not this NED contract. | R28: The South Region institutional agreement was reported complete. | S28: This creates an institutional workforce/research structure, though training targets are not yet completed outcomes. | T28: The contract milestone is stronger than an MoU, but it does not establish commencement, disbursement, laboratories, training or completed outputs; the NED contract value is undisclosed. | U28: Track contract publication, funding, labs, equipment, enrolment, completion and placements/research outputs. | V28: High | W28: Official PID release and procurement framework support contract status and downstream conditions; contract text and delivery evidence are absent. | X28: Contract text/value; commencement certificate; disbursement; lab specifications; delivery calendar; enrolment by cluster; outputs. | Y28: include | Z28: IN_SPAN_DEVELOPMENT
A29: EVT-PUNJAB-20260828-DATALAKE | B29: Punjab announces Data Lake and OneMap integration claims | C29: DIGITAL_IDENTITY_DPI | D29: Government of Punjab | E29: Punjab / Lahore; announcement at Guiyang event | F29: 46262 | G29: 46262 | H29: 2026-08-28T14:52Z (B009) | I29: 2026-09-01T16:51Z (B013) | J29: B009; B010; B013 | K29: S058 | L29: https://www.app.com.pk/punjab/maryam-delivers-thought-provoking-address-at-big-data-industry-expo/ | O29: officially claimed launch/integration; technical operation unverified | P29: APP relays Punjab claims of more than 12 TB of geospatial data, 31 departments and over 6,000 datasets in a Data Lake/OneMap context, alongside sovereign-cloud and AI-office ambitions. | R29: The province publicly framed a cross-department data platform as a delivery milestone. | S29: Centralised geospatial/government data can improve planning while magnifying legal-basis, access, security, correction and reuse risks. | T29: Treat quantities as government claims; no technical acceptance, architecture or legal instrument was located. | U29: Verify datasets, controllers, hosting, access, audit, retention, public transparency and acceptance tests. | V29: Medium | W29: Official news-agency report; underlying technical and legal evidence unavailable. | X29: Legal basis; architecture; dataset inventory; hosting; access; retention; audit; procurement; acceptance. | Y29: include | Z29: IN_SPAN_DEVELOPMENT
A30: EVT-KP-20260828-DIGITAL-DELIVERY | B30: KP government reports digital-service and cyber delivery | C30: DIGITAL_IDENTITY_DPI | D30: Government of Khyber Pakhtunkhwa | E30: Khyber Pakhtunkhwa | F30: 46261 | G30: 46262 | H30: 2026-08-28T14:52Z (B009) | I30: 2026-08-28T14:52Z (B009) | J30: B009 | K30: S059 | L30: https://dgipr.kp.gov.pk/stit-28-8-26/ | M30: S091 | N30: https://tribune.com.pk/story/2626183/citizen-facilitation-centres-planned?amp=1 | O30: district-centre directive plus provincial self-report; outcomes not independently verified | P30: At a 27 August performance briefing, the minister directed establishment of citizen facilitation centres in every district. The department also self-reported six model IT labs in merged-district schools, six digitised departments, an established Cyber Response Emergency Centre and a Peshawar citizen centre ready for inauguration. | R30: A new province-wide facilitation-centre directive was issued while earlier delivery items were restated as institutional claims. | S30: The portfolio suggests subnational service capacity but cannot be compared without budgets, service volumes and outcome measures. | T30: Institutional self-report is evidence of a claim, not independent proof of effectiveness. | U30: Obtain project lists, budgets, named sites, usage, uptime, incident and outcome metrics. | V30: Medium | W30: Official provincial statement supports the meeting and directive; operational assertions are not independently audited. | X30: District rollout plan; budgets; centre list; opening dates; service volumes; uptime; cybersecurity outcomes; independent validation. | Y30: include | Z30: IN_SPAN_DEVELOPMENT
A31: EVT-PUNJAB-20260828-HUAWEI | B31: Punjab and Huawei announce AI-training commitments and discuss data centres | C31: FUNDING_INVESTMENT_PARTNERSHIP | D31: Government of Punjab; Huawei | E31: Punjab / Nawaz Sharif IT City | F31: 46262 | G31: 2026-08-28; secondary report 2026-08-29 | H31: 2026-08-29T14:38Z (B010) | I31: 2026-08-29T14:38Z (B010) | J31: B010 | K31: S092 | L31: https://www.app.com.pk/punjab/punjab-cm-huawei-agree-to-expand-ai-digital-cooperation/ | M31: S060 | N31: https://www.brecorder.com/news/40436971/punjab-huawei-agree-to-expand-ai-digital-cooperation | O31: government–vendor meeting and announced commitments; no signed instrument or award | P31: APP reports a 28 August meeting and commitments to train 1,000 Punjab youth as Huawei master trainers and 300 women trainers in AI. Six data centres, including a sovereign centre at Nawaz Sharif IT City, were discussed; an AI Delivery Unit was proposed; Punjab stated a 2029 target for an AI-integrated system. | Q31: The sources do not clarify whether the 300 women are included within or additional to the 1,000 youth. Separate language describing a four-tier system is not evidence of a Tier IV data-centre classification. | R31: Training commitments and infrastructure proposals were announced at a meeting, without a published MoU, contract, financing or delivery schedule. | S31: Vendor concentration, procurement, data residency, power and exit terms would be material if the proposal advances. | T31: Do not count six operational data centres or committed capacity from this report. | U31: Seek the agreement, financing, sites, capacity, procurement route, power plan, safeguards and acceptance milestones. | V31: Medium | W31: Government-side APP account verifies the announcement; Huawei confirmation and operative instruments are absent, and delivery confidence is low. | X31: Signed text; financing; sites; capacity; procurement; power; data controls; delivery. | Y31: include with qualification | Z31: IN_SPAN_DEVELOPMENT
A32: EVT-PUNJAB-20260830-ALIBABA | B32: Punjab and Alibaba Cloud discuss AI public-service partnership | C32: FUNDING_INVESTMENT_PARTNERSHIP | D32: Government of Punjab; Alibaba Cloud | E32: Punjab / meeting in China | F32: 46264 | G32: 46264 | H32: 2026-08-30T14:57Z (B011) | I32: 2026-08-31T14:55Z (B012) | J32: B011; B012 | K32: S061; S062 | L32: https://www.app.com.pk/punjab/alibaba-cloud-shows-keen-interest-in-punjabs-it-sector-cm-maryam-invites-chinese-ai-collaboration/ | https://radio.gov.pk/30-08-2026/ai-being-integrated-into-governance-system-in-punjab-cm | M32: S093; S094 | N32: https://tribune.com.pk/story/2626664/chinese-firm-shows-interest-in-punjab-it-sector?amp=1 | https://radio.gov.pk/24-05-2026/pakistan-alibaba-group-ink-agreements-to-boost-digital-economy-cooperation | O32: exploratory discussion / potential partnership | P32: Official media report a 30 August exploratory meeting on a potential strategic partnership using AI in agriculture, healthcare, socio-economic programmes and climate forecasting; an Alibaba executive said data-centre discussions were under way. | Q32: The executive's reference to an MoU signed before the prime minister appears to concern earlier national agreements, not a new Punjab agreement on 30 August. | R32: A vendor-government discussion occurred; no signed text, workload or implementation followed in the period. | S32: Potential public-service AI creates procurement, hosting, transfer, accountability and vendor-exit questions. | T32: The available evidence supports exploration, not an operational deployment. | U32: Track agreement, site, financing, datasets, model governance, procurement, hosting and acceptance. | V32: Medium | W32: Two official-state reports align on a discussion; implementation evidence absent. | X32: Any new signed text; relationship to May national agreements; scope; financing; capacity; data flows; models; hosting; procurement; launch. | Y32: include | Z32: IN_SPAN_DEVELOPMENT
A33: EVT-KP-20260828-WORLDBANK-DIGITAL-ENERGY | B33: KP–World Bank talks link digital infrastructure, AI and energy | C33: FUNDING_INVESTMENT_PARTNERSHIP | D33: Government of Khyber Pakhtunkhwa; World Bank | E33: Khyber Pakhtunkhwa / Peshawar | F33: 2026-08-28 (page says Friday) | G33: 46265 | H33: 2026-08-31T14:55Z (B012) | I33: 2026-09-03T02:21Z (B014) | J33: B012; B014 | K33: S063 | L33: https://dgipr.kp.gov.pk/world-bank-delegation-meets-khyber-pakhtunkhwa-government-to-discuss-it-digital-infrastructure-and-energy-initiatives/ | M33: S095 | N33: https://www.brecorder.com/news/40437177/advisor-cs-kp-world-bank-team-discuss-it-digital-infrastructure-list-6 | O33: exploratory meeting; joint working group agreed; no financing | P33: The provincial release was published 31 August and says the meeting occurred Friday, which resolves to 28 August. It reports agreement to create a joint working group to examine technical and other modalities around digital transformation, AI, a KP data centre, hydropower and transmission. | R33: The parties agreed an exploratory working-group mechanism; no World Bank finance, project approval, assessment, site or technical parameters were disclosed. | S33: The linkage recognizes that compute infrastructure depends on reliable power and transmission. | T33: It is planning-stage evidence, not World Bank financing or a data-centre commitment. | U33: Track formal assessment, working group, finance, site, load, grid and safeguards. | V33: Medium | W33: Official provincial release and calendar inference support the meeting and working group; no World Bank source independently confirms it. | X33: World Bank confirmation; working-group terms; assessment; financing; site; capacity; energy plan. | Y33: include | Z33: IN_SPAN_DEVELOPMENT
A34: EVT-INTL-20260901-SAUDI-CLOUD-MEETING | B34: Pakistan and Saudi Arabia announce deeper cloud and cybersecurity cooperation | C34: FUNDING_INVESTMENT_PARTNERSHIP | D34: MoITT; Saudi Ministry of Communications and Information Technology | E34: Riyadh / Pakistan–Saudi | F34: 46266 | G34: 46266 | H34: 2026-09-01T16:51Z (B013) | I34: 2026-09-01T16:51Z (B013) | J34: B013 | K34: S064 | L34: https://www.app.com.pk/national/shaza-meets-saudi-minister-of-communications-and-information-technology/ | O34: ministerial cooperation announcement; no cloud project instrument | P34: APP reports that ministers agreed to enhance cooperation in cloud infrastructure and cybersecurity and discussed B2B partnerships, technology exports, investment, skills and technology transfer. | R34: A ministerial cooperation statement entered the record. | S34: It could open investment and export channels, but no cloud workload, capital commitment, safeguards or timetable exists in the evidence. | T34: This cloud-cooperation announcement is separate from the Saudi NCA–MoITT cybersecurity MoU and should not be converted into a funded infrastructure project. | U34: Track instrument, counterparties, workplan, financing, hosting, transfers, security and exit terms. | V34: Medium | W34: Official news-agency report; no bilateral text or project documentation. | X34: Instrument; projects; finance; parties; workplan; hosting; data transfers; cybersecurity obligations. | Y34: include | Z34: IN_SPAN_DEVELOPMENT
A35: EVT-INTL-20260901-SAUDI-NCA-CYBER-MOU | B35: Saudi NCA and Pakistan MoITT sign cybersecurity MoU | C35: CYBERSECURITY | D35: Saudi National Cybersecurity Authority; Pakistan Ministry of IT and Telecommunication | E35: Riyadh / Pakistan–Saudi | F35: 46266 | G35: 2026-09-01; Pakistani corroboration 2026-09-02 | H35: 2026-09-03T04:15Z (verification; not captured in B001–B014) | I35: 2026-09-03T04:15Z (verification) | K35: S096 | L35: https://nca.gov.sa/ar/news/2581/ | M35: S097; S098 | N35: https://www.radio.gov.pk/02-09-2026/pakistan-saudi-arabia-sign-mou-in-area-of-cybersecurity | https://www.app.com.pk/national/pakistan-saudi-arabia-sign-cybersecurity-agreement/ | O35: signed bilateral cybersecurity MoU; implementation not evidenced | P35: The Saudi National Cybersecurity Authority and Pakistan's MoITT signed a cybersecurity MoU on 1 September in Riyadh. The Saudi authority's page is dated 1 September and was last modified at 16:23 AST; Pakistani official outlets corroborated the signing on 2 September. | Q35: Official accounts describe cooperation in cybersecurity without publishing the full instrument. | R35: A formal bilateral cybersecurity instrument was signed; the supplied briefing set missed it despite covering adjacent Saudi meetings. | S35: The event is substantively stronger than a ministerial discussion and exposes the monitoring corpus's severe cadence and discovery gaps. | T35: Signed-instrument status is verified, but no operational programme, budget or transfer mechanism should be inferred. | U35: Obtain the MoU, term, workplan, participating agencies, funding, information-sharing rules, data safeguards and delivery evidence. | V35: High | W35: A first-party Saudi authority release and two Pakistani official sources independently confirm signing; implementation particulars are absent. | X35: Full text; term; workplan; financing; data-sharing; operational mechanism; outputs. | Y35: include; verification-discovered event absent from briefing corpus | Z35: IN_SPAN_DEVELOPMENT
A36: EVT-INTL-20260901-SAUDI-SDAIA-AI-DATA | B36: Pakistan and Saudi data authority discuss AI and data-governance cooperation | C36: DATA_PROTECTION_GOVERNANCE | D36: Pakistan MoITT; Saudi Data and Artificial Intelligence Authority | E36: Riyadh / Pakistan–Saudi | F36: 46266 | G36: 46266 | H36: 2026-09-03T04:15Z (verification; not captured in B001–B014) | I36: 2026-09-03T04:15Z (verification) | K36: S109 | L36: https://www.app.com.pk/national/pakistan-saudi-arabia-agree-to-strengthen-cooperation-in-ai-data-governance/ | O36: exploratory official meeting; no instrument or project | P36: APP reports a 1 September meeting between Pakistan's IT minister and the Saudi Data and Artificial Intelligence Authority on possible cooperation in AI and data governance. | R36: A separate AI/data-governance dialogue appeared during verification but was absent from the briefing corpus. | S36: It signals international policy coordination, while the absence of an instrument leaves obligations and implementation undefined. | T36: Treat as agenda-setting, not a signed agreement, funded programme or shared-data arrangement. | U36: Track any signed instrument, workplan, standards alignment, cross-border data terms, projects, financing and safeguards. | V36: Medium | W36: An official news-agency report verifies the meeting; no Saudi first-party confirmation or instrument was located. | X36: Counterparty confirmation; instrument; workplan; projects; financing; data transfers; safeguards. | Y36: include with qualification; verification-discovered event absent from briefing corpus | Z36: IN_SPAN_DEVELOPMENT
A37: EVT-DPI-20260901-OPEN-STACK | B37: Pakistan says national digital stack is under development and may be shared when complete | C37: DIGITAL_IDENTITY_DPI | D37: MoITT; Pakistan Digital Authority | E37: Riyadh announcement / international recipients | F37: 46266 | G37: 46266 | H37: 2026-09-01T16:51Z (B013) | I37: 2026-09-01T16:51Z (B013) | J37: B013 | K37: S099 | L37: https://moitt.gov.pk/NewsDetail/NWI0ZjIwOTctYzc1Ny00NzBkLTliNGQtMzc2NWQxOTQyMzlk | M37: S065 | N37: https://www.arabnews.pk/pakistan/minister-tells-saudi-expo-pakistan-will-share-digital-infrastructure-free-with-emerging-economies-3000008 | O37: under development; future sharing intention; not released or deployed | P37: MoITT says Pakistan is developing a national digital stack spanning identity, data and payments and intends to share it free with frontier and emerging economies when complete. The event pavilion included 25 startups and 50 Pakistani technology firms; those are event-context figures, not stack capacity. | R37: An outward-facing future-sharing intention was announced while the official source expressly described the stack as unfinished. | S37: Exportable DPI could create interoperability and influence, but also transfers domestic governance assumptions across jurisdictions. | T37: No released code, licence, completed system or international deployment exists in the evidence; free-to-share is not yet a verified open-source release. | U37: Verify repositories, licence, architecture, security audit, recipients, budget and pilots. | V37: High | W37: Official ministry source directly states the under-development status; completion and future sharing remain unverified. | X37: Code; licence; readiness; architecture; recipients; security; privacy; audited pilots. | Y37: include with qualification | Z37: IN_SPAN_DEVELOPMENT
A38: EVT-PUNJAB-20260902-AUQAF-AI | B38: Punjab Auqaf reports AI-assisted monitoring at model shrines | C38: AI_GOVERNANCE | D38: Punjab Auqaf and Religious Affairs Department | E38: Punjab | F38: 46267 | G38: 46267 | H38: 2026-09-03T02:21Z (B014) | I38: 2026-09-03T02:21Z (B014) | J38: B014 | K38: S066 | L38: https://auqaf.punjab.gov.pk/node/835 | O38: authority-reported operation; system assurance unavailable | P38: The department says digital monitoring is operational and that 10 of 16 model shrines are connected, naming sites including Badshahi Mosque and Baba Bulleh Shah’s shrine. | Q38: The authority labels the system AI-based. | R38: A provincial department reported a live deployment footprint. | S38: Monitoring in religious/public spaces raises proportionality, biometric, retention, security, accuracy and redress issues. | T38: Operational scope and AI function remain unverified beyond the department’s account. | U38: Obtain procurement, vendor, model/function description, legal basis, data map, retention, audit and complaints process. | V38: Medium | W38: Official authority statement; no independent system evidence or assurance artefacts. | X38: Vendor; contract; AI function; biometrics; lawful authority; retention; accuracy; human review; redress. | Y38: include | Z38: IN_SPAN_DEVELOPMENT
A39: EVT-PUNJAB-20260902-PBTE-DIGITISATION | B39: PBTE reports examination digitisation and assigns policy review | C39: DIGITAL_IDENTITY_DPI | D39: Punjab Board of Technical Education; Punjab Industries Department | E39: Punjab | F39: 46267 | G39: 46267 | H39: 2026-09-03T02:21Z (B014) | I39: 2026-09-03T04:15Z (verification) | J39: B014 | K39: S100; S067 | L39: https://www.app.com.pk/business/punjab-industries-minister-chairs-pbte-board-meeting/ | https://vid.app.com.pk/vid/2026/09/%D8%B5%D9%88%D8%A8%D8%A7%D8%A6%DB%8C-%D9%88%D8%B2%DB%8C%D8%B1-%D8%B5%D9%86%D8%B9%D8%AA-%D9%88-%D8%AA%D8%AC%D8%A7%D8%B1%D8%AA-%DA%86%D9%88%D8%AF%DA%BE%D8%B1%DB%8C-%D8%B4%D8%A7%D9%81%D8%B9-%D8%AD-41/ | O39: board meeting and authority-reported digitisation; policies assigned for review, not finalised | P39: APP reports a 15-point PBTE board agenda and authority claims that examination-centre monitoring, e-marking and digital paper transmission had been introduced. Eleven assessment and certification policies were assigned for review rather than approved as final instruments. | R39: PBTE reported digitisation measures and initiated policy review; no system acceptance or final policy text was produced. | S39: Digital examination systems affect integrity, access, security, auditability and student redress. | T39: Institutional self-report is not independent proof of system performance, and assignment for review is not policy adoption. | U39: Track system procurement, operating scope, security and accessibility testing, incident records, final policy approval and publication. | V39: Medium | W39: Official news-agency account verifies the meeting and claims; underlying systems and policy texts are unavailable. | X39: System/vendor details; legal basis; acceptance tests; security; accessibility; audit; final policy texts. | Y39: include | Z39: IN_SPAN_DEVELOPMENT
A40: EVT-PUNJAB-20260902-PTUT-AI-COURSES | B40: Punjab minister announces planned PTUT AI courses | C40: WORKFORCE_RESEARCH_EDUCATION | D40: Punjab Tianjin University of Technology; Punjab Industries Department | E40: Punjab | F40: 46267 | G40: 46267 | H40: 2026-09-03T02:21Z (B014; originally conflated with PBTE) | I40: 2026-09-03T04:15Z (verification) | J40: B014 | K40: S100; S067 | L40: https://www.app.com.pk/business/punjab-industries-minister-chairs-pbte-board-meeting/ | https://vid.app.com.pk/vid/2026/09/%D8%B5%D9%88%D8%A8%D8%A7%D8%A6%DB%8C-%D9%88%D8%B2%DB%8C%D8%B1-%D8%B5%D9%86%D8%B9%D8%AA-%D9%88-%D8%AA%D8%AC%D8%A7%D8%B1%D8%AA-%DA%86%D9%88%D8%AF%DA%BE%D8%B1%DB%8C-%D8%B4%D8%A7%D9%81%D8%B9-%D8%AD-41/ | O40: ministerial launch intention for September; delivery not evidenced | P40: The minister said AI courses were being launched during September at Punjab Tianjin University of Technology. The announcement did not identify course titles, intake, budget, faculty or a confirmed first class. | R40: A provincial workforce intention was announced for PTUT, distinct from the PBTE board action described in the same report. | S40: Technical-education pathways could broaden skills supply, but no scale or delivery can yet be assessed. | T40: A planned launch is not enrollment, instruction or completion, and the programme should not be attributed to PBTE. | U40: Track university notification, curricula, instructors, budget, enrolment, first teaching date and outcomes. | V40: Low | W40: Official news-agency account supports the ministerial statement; no university artefact or delivery evidence was found. | X40: Notification; curriculum; intake; faculty; budget; enrolment; start date; completion and placement outcomes. | Y40: include with qualification | Z40: IN_SPAN_DEVELOPMENT
A41: BASE-AIPOL-20250730-31 | B41: National Artificial Intelligence Policy 2025 approved | C41: AI_GOVERNANCE | D41: Federal Cabinet; MoITT | E41: Federal / Pakistan | F41: 2025-07-30/31 | G41: 2025-07-31; 2025-07-30 | H41: 2026-08-18T19:38Z (B001) | I41: 2026-09-03T02:21Z (B014) | J41: B001; B002; B003; B004; B005; B006; B007; B008; B009; B010; B011; B012; B013; B014 | K41: S001; S002 | L41: https://www.moitt.gov.pk/Policies | https://www.moitt.gov.pk/SiteImage/Policies/National%20AI%20Policy.pdf | M41: S003 | N41: https://www.radio.gov.pk/30-07-2025/federal-cabinet-approves-hajj-policy-2026-artificial-intelligence-policy-2025 | O41: approved policy; implementation instruments not located | P41: MoITT marks the policy Approved with 31 July 2025 approval date; Radio Pakistan reports Cabinet approval on 30 July. The policy envisages an AI Council, implementation cell, action matrix, funds, sandboxes and a public AI register. | R41: No separate constitutive or operating instrument for the major implementation mechanisms was located during the reporting span. | S41: The policy is the strategic baseline but does not itself prove funded programmes, institutions or enforcement. | T41: Keep policy approval distinct from execution. | U41: Track constitutive notices, budgets, action matrix, sandboxes, register and delivery metrics. | V41: High | W41: Official policy register and text; implementation non-location is bounded. | X41: One-day approval-date discrepancy; Council/cell/fund constitution; budget; master plan; implementation evidence. | Y41: include as baseline | Z41: BASELINE_CARRY_IN
A42: BASE-AIBILL-20240909 | B42: Regulation of Artificial Intelligence Bill, 2024 withdrawn/disposed | C42: AI_GOVERNANCE | D42: Senate of Pakistan | E42: Federal / Pakistan | F42: 45544 | G42: live or undated source; see source register | H42: 2026-08-18T19:38Z (B001) | I42: 2026-08-21T15:05Z (B003) | J42: B001; B002; B003 | K42: S004 | L42: https://www.senate.gov.pk/en/billsummary.php?bid=1544 | O42: withdrawn/disposed; not enacted | P42: The Senate records introduction and referral on 9 September 2024, committee inaction, and withdrawal/disposal under standing orders. | R42: No successor AI statute was verified during the period. | S42: Pakistan’s AI policy does not rest on this withdrawn bill as an operative law. | T42: Do not cite it as enacted authority. | U42: Track any new federal AI bill from introduction onward. | V42: High | W42: Official parliamentary disposition. | X42: Any successor legislative proposal. | Y42: include as legal baseline | Z42: BASELINE_CARRY_IN
A43: BASE-DGP-20260626 | B43: National Data Governance Policy 2026 remains draft/finalisation-stage | C43: DATA_PROTECTION_GOVERNANCE | D43: MoITT; PDA | E43: Federal / Pakistan | F43: 2026-06-26 to 2026-08-21 | G43: 2026-06-30; 2026-08-05; 2026-08-21 | H43: 2026-08-18T19:38Z (B001) | I43: 2026-09-03T02:21Z (B014) | J43: B001; B002; B003; B004; B005; B006; B007; B008; B009; B010; B011; B012; B013; B014 | K43: S001; S009; S010; S011 | L43: https://www.moitt.gov.pk/Policies | https://www.pda.gov.pk/press-details.php?id=data-governance-policy | https://pda.gov.pk/press-details.php?id=pda-dgp-consultation | https://pda.gov.pk/press-details.php?id=from-fragmentation-to-federation | O43: draft; consultation concluded; finalisation pending | P43: MoITT currently labels Data Governance Policy 2026 Draft, dated 26 June. PDA invited comments on 30 June, said on 5 August it would incorporate feedback before finalising, and still used draft language on 21 August. | R43: No approval, notification or commencement evidence was found. | S43: Government data-sharing initiatives remain ahead of a final national governance policy. | T43: Final-stage process language is not final issuance. | U43: Track final text, approval, notification, implementation plan and institutional mandates. | V43: High | W43: Multiple current official sources align on draft/finalisation status. | X43: Final text; approval; notification; commencement; implementation plan. | Y43: include as baseline | Z43: BASELINE_CARRY_IN
A44: BASE-PDP-2023-2026 | B44: No enacted horizontal personal-data law verified | C44: DATA_PROTECTION_GOVERNANCE | D44: MoITT; Parliament | E44: Federal / Pakistan | F44: 2018-2026 lineages | G44: 46156 | H44: 2026-08-18T19:38Z (B001) | I44: 2026-09-03T02:21Z (B014) | J44: B001; B002; B003; B004; B005; B006; B007; B008; B009; B010; B011; B012; B013; B014 | K44: S005; S006; S007; S008; S085 | L44: https://www.moitt.gov.pk/Legislations | https://na.gov.pk/uploads/documents/6a1d62bdce349_708.pdf | https://senate.gov.pk/en/pbs.php?catid=1&cattitle=Bills&leftcatid=278&subcatid=276 | https://senate.gov.pk/en/acts.php | https://www.na.gov.pk/en/acts.php | O44: multiple drafts/withdrawn bill; no Act verified | P44: MoITT lists 2018, 2020 and May 2023 executive drafts. A separate 2023 private member’s bill was withdrawn/disposed. A May 2026 parliamentary answer says MoITT finalised a bill/proposal, while current Acts registers show no horizontal Personal Data Protection Act. | R44: No passage, assent, Gazette or commencement was verified in the supplied span. | S44: Public-sector data integration, AI and cloud activity continue without a verified horizontal statute in force. | T44: Do not merge executive drafts, a withdrawn private bill and a ministry-finalised proposal into one legislative lifecycle. | U44: Track an introduced government bill, committee text, passage, assent, Gazette and commencement. | V44: Medium | W44: Official registers support the lineage and non-enactment; negative finding is bounded to registers checked. | X44: Current government bill text; Cabinet approval; introduction; parliamentary path; transition rules. | Y44: include as legal baseline | Z44: BASELINE_CARRY_IN
A45: BASE-PISF-20260810-11 | B45: Pakistan Information Security Framework 2026 approved and published | C45: CYBERSECURITY | D45: Federal Cabinet; PKCERT | E45: Federal / covered public and CII entities | F45: 2026-08-10/11 | G45: 2026-08-11; 2026 | H45: 2026-08-18T19:38Z (B001) | I45: 2026-09-03T02:21Z (B014) | J45: B001; B013; B014 | K45: S012; S013; S014 | L45: https://www.moib.gov.pk/News/66315 | https://pkcert.gov.pk/grc-policies.asp | https://pkcert.gov.pk/uploads/2026/03/PISF_Merged-Version.pdf | M45: S015 | N45: https://www.dawn.com/news/2022051/cabinet-okays-housing-policy-cybersecurity-framework | O45: Cabinet-approved and published framework; legal force qualified | P45: PKCERT publishes the revised framework and control suite. The text uses mandatory baseline language for federal/provincial ministries, departments, autonomous bodies, corporations, CERTs and designated CII, with oversight/audit roles. Government and news reporting describe Cabinet approval. | R45: No standalone PISF SRO or implementation report was located in the monitoring period. | S45: The framework provides a concrete public-sector/CII security baseline but is not a generally applicable private-sector statute. | T45: Stronger than aspiration for expressly covered entities; exact enforcement route requires qualification. | U45: Track implementing directions, audit results, sectoral adoption, incidents and enforcement. | V45: High | W45: Official framework text and register; medium confidence on enforceability absent standalone notification. | X45: Exact Cabinet date; standalone notification; audit/enforcement practice; coverage designations. | Y45: include as baseline | Z45: BASELINE_CARRY_IN
A46: BASE-DNP-WASL-20260426-0513 | B46: DNP/WASL standards remain Pilot; supporting documents remain working drafts | C46: DIGITAL_IDENTITY_DPI | D46: PDA / Digital Nation Pakistan | E46: Federal / pilot participants | F46: 2026-04-26 and 2026-05-13 | G46: live or undated source; see source register | H46: 2026-08-24T19:25Z (B006) | I46: 2026-09-03T02:21Z (B014) | J46: B006; B007; B009; B010; B011; B012; B014 | K46: S016 | L46: https://standards.dnp.gov.pk/register.html | O46: Pilot publications; not gazetted regulatory class | P46: The register shows DNP-X.001 and DNP-D.002 as Pilot/PUB dated 13 May, and DNP-D.250 and DNP-D.300 as Pilot/WD dated 26 April. The framework defines Pilot as mandatory only for pilot participants; REG is the legally binding gazetted class. | R46: No final REG instrument or separate participation regulation appeared. | S46: Identity/data-exchange architecture is being piloted before a final binding framework is visible. | T46: Published architecture is not equivalent to generally binding participation rules. | U46: Track DNP-D.050 REG, participation regulation, security audits and production onboarding. | V46: High | W46: Official standards register and documents. | X46: Missing referenced DNP-D.050 REG; participation rules; production scope; audits. | Y46: include as baseline | Z46: BASELINE_CARRY_IN
A47: BASE-ETDC-20260618-25 | B47: Emerging Technologies Data Centre recommended to ECNEC and entered PSDP | C47: COMPUTE_CLOUD_DATACENTRE | D47: Planning Commission; Defence Division / Ministry of Defence | E47: Federal / Pakistan | F47: official portfolio action 2026-06-18; public announcement 2026-06-25 | G47: 2026-06-25; 2026-07; 2026 | H47: 2026-08-18T19:38Z (B001) | I47: 2026-09-03T02:21Z (B014) | J47: B001; B006; B007; B010; B013; B014 | K47: S068; S105; S106; S107; S108 | L47: https://www.pc.gov.pk/web/press/get_press/1702 | https://pid.gov.pk/site/press_detail/33093 | https://pc.gov.pk/uploads/pub/Monthly-Development-Update-July-2026.pdf | https://pc.gov.pk/uploads/archives/PSDP_2026-27_Final.pdf | https://pc.gov.pk/uploads/annualplan/Annual-Plan-2026-27.pdf | O47: CDWP in-principle approval / recommendation to ECNEC; PSDP-allocated; ECNEC approval unverified | P47: Official portfolio records give an exact project cost of PKR 7,930.000 million and date the CDWP action 18 June, while contemporaneous Planning Commission and PID releases dated 25 June say the committee met that day. The final PSDP lists ETDC under Defence Division new schemes with zero expenditure through 30 June, a PKR 7,930 million throw-forward and PKR 100 million FY2026–27 allocation. | Q47: The project is described as a secure, sovereign, government-owned AI and high-performance-computing facility for cloud, analytics, government, academia, research and private-sector use. | R47: No later ECNEC approval, fund release, procurement, construction, commissioning or acceptance was located through the cutoff. | S47: It is a potential public compute anchor, but a budget allocation and referral add no usable compute capacity. | T47: Preserve the official date conflict and separate recommendation, allocation, release, expenditure, construction, commissioning and utilization. | U47: Track ECNEC decision, revised PC-I, releases, procurement, site, power, cooling, connectivity, GPU inventory and acceptance. | V47: High | W47: Multiple official planning and budget documents confirm cost, referral and allocation; implementation confidence remains low. | X47: Correct committee date; ECNEC decision; releases; PC-I; site; MW/IT load; GPUs; delivery; utilization. | Y47: include as baseline | Z47: BASELINE_CARRY_IN
A48: BASE-NAIEDP-20260625 | B48: National AI Ecosystem Development Program proposal considered by CDWP | C48: PROCUREMENT_PROGRAM_DELIVERY | D48: Planning Commission; MoITT | E48: Federal / Pakistan | F48: 46198 | G48: 46198 | H48: 2026-08-18T19:38Z (B001) | I48: 2026-09-03T02:21Z (B014) | J48: B001; B006; B007; B010; B013; B014 | K48: S068 | L48: https://www.pc.gov.pk/web/press/get_press/1702 | O48: PKR 13 billion in-principle/recommended to ECNEC; not delivered | P48: The Planning Commission release describes a PKR 13 billion programme including a feasibility study and upgraded PC-I, recommended onward rather than finally delivered. | R48: No final approval, release, award or output was verified. | S48: It may become a national programme vehicle, but pipeline status is upstream of spending and outcomes. | T48: Planning approval language must not be treated as a funded programme. | U48: Track ECNEC, PC-I, releases, procurement and outcome metrics. | V48: High | W48: Official planning release supports amount and stage. | X48: ECNEC decision; funding release; programme design; procurement; outputs. | Y48: include as baseline | Z48: BASELINE_CARRY_IN
A49: BASE-SOVAI-RFP-20260724 | B49: Sovereign National AI Infrastructure RFP remains open | C49: COMPUTE_CLOUD_DATACENTRE | D49: Ignite National Technology Fund | E49: Federal / Pakistan | F49: 2026-07-24 to 2026-09-21 | G49: 46227 | H49: 2026-08-18T19:38Z (B001) | I49: 2026-09-03T02:21Z (B014) | J49: B001; B005; B009; B010; B011; B012; B014 | K49: S069 | L49: https://epms.ppra.gov.pk/public/tenders/tender-details/TS0000010170E | O49: open RFP; pre-award | P49: RFP P57167 covers design, deployment, operation and maintenance of sovereign national AI infrastructure, with PKR 2 million bid security, 360-day bid validity and a 21 September 2026 15:00 PKT deadline. | Q49: The portal labels 21 September as Wednesday; calendar verification shows Monday. | R49: No award or delivery milestone occurred within the reporting span. | S49: This is the clearest federal procurement pathway toward national AI compute, but no capacity exists yet from the tender. | T49: Do not infer GPUs, MW, users or availability before contract and acceptance. | U49: Track bids, evaluation, award, architecture, site, power/cooling, access model and acceptance. | V49: High | W49: Official tender record; weekday metadata error explicitly corrected. | X49: Bidders; award; value; architecture; capacity; location; energy; access; acceptance. | Y49: include as baseline | Z49: BASELINE_CARRY_IN
A50: BASE-PITB-AICLOUD-20260731 | B50: PITB Government AI Cloud consultancy tender has conflicting closing dates | C50: COMPUTE_CLOUD_DATACENTRE | D50: Punjab Information Technology Board | E50: Punjab | F50: 2026-07-31 to 2026-08-24 | G50: live or undated source; see source register | H50: 2026-08-18T19:38Z (B001) | I50: 2026-08-28T14:52Z (B009) | J50: B001; B002; B003; B004; B005; B006; B007; B008; B009 | K50: S070 | L50: https://pitb.gov.pk/tendernotices | O50: closed/pre-award; tender identity/date conflict | P50: The corpus alternately records 17 and 24 August closing dates, with later snapshots treating 24 August as closed and no result visible. | R50: No evaluation, award or deployment was authenticated. | S50: The consultancy may shape Punjab cloud design, but inconsistent metadata prevents a clean procurement timeline. | T50: Preserve competing dates until the bid document/corrigendum chain is recovered. | U50: Retrieve tender ID, bid document, corrigenda, opening, evaluation and award. | V50: Low | W50: Official listing exists, but the dataset’s dates conflict and durable document identity is unresolved. | X50: Tender ID; governing deadline; scope; evaluation; award; architecture; safeguards. | Y50: include as disputed baseline | Z50: CONTRADICTED_OR_UNRESOLVED
A51: BASE-PITB-DC11 | B51: PITB DC-11 GPU server tender closed | C51: COMPUTE_CLOUD_DATACENTRE | D51: Punjab Information Technology Board | E51: Punjab | F51: 46205 | G51: 2026 | H51: 2026-08-18T19:38Z (B001) | I51: 2026-08-18T19:38Z (B001) | J51: B001 | K51: S071 | L51: https://pitb.gov.pk/system/files/BD_DC-11_Corrigen-Published.pdf | O51: closed procurement; no award verified | P51: The DC-11 document describes eight L20 servers (PKR 280 million), one H200 server (PKR 100 million) and two unspecified GPU servers (PKR 600 million), totalling PKR 980 million; the tender closed 2 July. | R51: No in-span result was found. | S51: It is a concrete proposed GPU package but not delivered compute. | T51: Do not transfer quantities/value to the separate DC-02 or ITOPS-23 procurements. | U51: Track evaluation, award, delivery, site, power/cooling and acceptance. | V51: High | W51: Official bid document; downstream status absent. | X51: Award; vendor; delivery; site; accepted GPU capacity. | Y51: include as baseline | Z51: BASELINE_CARRY_IN
A52: BASE-PITB-DC02 | B52: PITB DC-02 GPU server procurement remains separately identified | C52: COMPUTE_CLOUD_DATACENTRE | D52: Punjab Information Technology Board | E52: Punjab | F52: 2026-08-31 (reported closing) | G52: live or undated source; see source register | H52: 2026-08-20T14:50:39Z (B002) | I52: 2026-08-28T14:52Z (B009) | J52: B002; B003; B004; B005; B006; B007; B008; B009 | K52: S070 | L52: https://pitb.gov.pk/tendernotices | O52: reported closed; document identity/results unresolved | P52: Briefing snapshots describe a separate later GPU-server procurement closing 31 August. | R52: No verified evaluation or award appeared. | S52: Keeping it separate prevents false aggregation of procurement value and hardware. | T52: Quantities from DC-11 cannot be imputed to DC-02. | U52: Recover direct tender document and result. | V52: Low | W52: Mutable listing/corpus reference without a durable direct document in the verified source set. | X52: Tender document; quantities; budget; evaluation; award; delivery. | Y52: watchlist baseline | Z52: CONTRADICTED_OR_UNRESOLVED
A53: BASE-PITB-ITOPS23 | B53: PITB ITOPS-23 AI-enabled data-centre package tender closed | C53: COMPUTE_CLOUD_DATACENTRE | D53: Punjab Information Technology Board | E53: Punjab | F53: 46204 | G53: 2026 | H53: 2026-08-18T19:38Z (B001) | I53: 2026-08-18T19:38Z (B001) | J53: B001 | K53: S072 | L53: https://pitb.gov.pk/system/files/BD_ITOPS_23_Corrigen_Published.pdf | O53: closed procurement; no award verified | P53: The bid document describes a PKR 600 million turnkey AI-enabled data-centre package with delivery within 24 weeks of award; it closed 1 July. | R53: No in-span award or accepted delivery was found. | S53: It is distinct from DC-11 GPU servers and the later DC-02 listing. | T53: Budgeted package is not commissioned infrastructure. | U53: Track evaluation, award, site, delivery, security and acceptance. | V53: High | W53: Official bid document; downstream status absent. | X53: Award; contract; site; equipment; delivery; acceptance. | Y53: include as baseline | Z53: BASELINE_CARRY_IN
A54: BASE-FINTECH-SUMMIT | B54: Pakistan FinTech Summit outcomes remain unverified | C54: FUNDING_INVESTMENT_PARTNERSHIP | D54: PDA; DIFC | E54: Pakistan / international | F54: 2026 planned | G54: 46076 | H54: 2026-08-18T19:38Z (B001) | I54: 2026-08-18T19:38Z (B001) | J54: B001 | K54: S073 | L54: https://www.difc.com/whats-on/news/difcs-dubai-fintech-summit-expands-globally-with-pakistan-digital-authority | O54: advance announcement only; occurrence and outcomes unverified | P54: DIFC published an advance expansion announcement involving PDA. | R54: No later agreement, investment, launch or outcome was authenticated in the supplied span. | S54: Advance event promotion cannot substantiate capital or programme outcomes. | T54: No event occurrence or material outcome should be inferred from the advance announcement. | U54: Seek event record and signed outcomes if any. | V54: High | W54: Direct advance announcement; no outcome evidence. | X54: Event occurrence; agreements; investments; launches. | Y54: retain as disputed baseline context; exclude asserted outcomes | Z54: CONTRADICTED_OR_UNRESOLVED
A55: BASE-SKY47-20260724-KARAKORAM01 | B55: Sky47 Karakoram-01 data centre inaugurated | C55: COMPUTE_CLOUD_DATACENTRE | D55: Sky47 | E55: Islamabad | F55: 46227 | G55: 2026-07-24; 2026-07-29; 2026 | H55: 2026-08-22T15:05Z (B004) | I55: 2026-09-01T16:51Z (B013) | J55: B004; B013 | K55: S052 | L55: https://www.radio.gov.pk/24-07-2026/pm-field-marshal-inaugurate-sky47-karakorum-01-data-centre | M55: S053; S054 | N55: https://www.datacenterdynamics.com/en/news/pakistani-operator-sky47-inaugurates-85mw-data-center-in-islamabad/ | https://dps.psx.com.pk/download/document/254563.pdf | O55: inaugurated baseline; utilisation and accepted IT load unverified | P55: Official and specialist reporting place the Karakoram-01 inauguration in Islamabad on 24 July; specialist reporting describes an 8.5 MW facility. | Q55: Company/exchange materials describe later Karachi and Lahore expansion plans. | R55: No new capacity activation was verified during the reporting span; the 21 August Commerce meeting was separate. | S55: It is the strongest private physical-infrastructure baseline in the corpus, but facility MW is not the same as available AI compute. | T55: Separate inauguration, design capacity, IT load, GPUs, customers and utilisation. | U55: Verify certification, commissioned IT load, power/cooling resilience, GPUs, customers and expansion completion. | V55: Medium | W55: Official inauguration plus specialist 8.5 MW reporting; detailed operational metrics absent. | X55: Gross vs IT load; GPU inventory; utilisation; customers; PPA; resilience; certification; expansions. | Y55: include as baseline | Z55: BASELINE_CARRY_IN
A56: BASE-GOOG-20260801-COMMERCIAL | B56: Google Pakistan (Private) Limited becomes counterparty for specified advertising products | C56: GOOGLE_CORPORATE_PRESENCE | D56: Google Pakistan (Private) Limited | E56: Pakistan / Sindh tax nexus | F56: 2026-08-01; invoicing transition 2026-10-01 | G56: live or undated source; see source register | H56: 2026-09-03T04:15Z (verification; not captured in B001–B014) | I56: 2026-09-03T04:15Z (verification) | K56: S080 | L56: https://support.google.com/google-ads/answer/2375370?hl=en-GB | O56: direct-company commercial/tax counterparty evidence; not physical-office evidence | P56: Google states that from 1 August 2026 its Pakistan private limited entity is the counterparty for new affected-product accounts; from 1 October it will issue invoices for existing Pakistani-billing-address, PKR, monthly-invoice accounts and charge 15% Sindh sales tax. Automatic/manual payment accounts remain contracted with Google Asia Pacific Pte. Ltd. | R56: A limited product/billing counterparty role became directly verifiable outside the briefing discovery set. | S56: This is concrete local commercial evidence, but it does not establish office premises, local employment or data hosting. | T56: Corporate/tax role and physical office must remain separate evidence categories. | U56: Track invoicing transition, entity disclosures, local contracting scope, employment and premises evidence. | V56: High | W56: Direct Google operational guidance with effective dates and product scope. | X56: Corporate registration record; address; staffing; employing role; broader product scope; data processing/hosting. | Y56: include as verification baseline | Z56: BASELINE_CARRY_IN

Sheet Coverage & Gaps
A1: Coverage & Gaps
A2: Formula-driven cadence reconciliation and every inter-briefing gap; missing intervals are not imputed.
A4: Cadence controls
A5: Metric | B5: Value | C5: Unit | D5: Basis
A6: Nominal expected briefing runs | B6: 1440 | C6: runs | D6: 15 days × 24 hours × 4 runs/hour
A7: Observed briefing units | B7: =COUNTA('Briefing Units'!$A$5:$A$18) -> 14 | C7: units | D7: Normalized B001–B014 rows
A8: Nominal missing runs | B8: =B6-B7 -> 1426 | C8: runs | D8: Nominal expected minus observed
A9: Observed share of nominal expected | B9: =IF(B6=0,0,B7/B6) -> 0.0097222222 | C9: share | D9: Divide-by-zero protected
A10: Observed span minutes | B10: 22017 | C10: minutes | D10: First normalized window start to last normalized window end
A11: Observed strict-window minutes | B11: 215.82 | C11: minutes | D11: Sum of explicit or reconstructed briefing windows
A12: Strict-window share of observed span | B12: =IF(B10=0,0,B11/B10) -> 0.0098024254 | C12: share | D12: Strict observed minutes ÷ observed span
A13: Expected runs across observed span | B13: 1468 | C13: runs | D13: Observed span at a 15-minute cadence
A14: Approximate missing across observed span | B14: =B13-B7 -> 1454 | C14: runs | D14: Span-based expected minus observed
A15: Observed share of span-based expected | B15: =IF(B13=0,0,B7/B13) -> 0.0095367847 | C15: share | D15: Divide-by-zero protected
A17: Normalized observation boundary
A18: Field | B18: Value | C18: Interpretation
A19: Observed start | B19: 46252.808 | C19: First normalized briefing-window start
A20: Observed end | B20: 46268.098 | C20: Last normalized briefing-window end
A21: Search cutoff | B21: 46268.177 | C21: Latest documented current-source verification time
A22: Normalized time zone | B22: UTC | C22: PKT equivalents remain visible on the Briefing Units sheet
A23: Timestamp policy | B23: Use explicit internal UTC/PKT windows as authoritative; treat filename dates/times and filesystem timestamps as discovery metadata only; label reconstructed endpoints approximate. | C23: Filename and filesystem timestamps are discovery metadata only
A24: Title dates without a briefing | B24: 2026-08-19, 2026-08-24 | C24: Nominal title-date comparison only
A25: PKT dates without a normalized window | B25: 2026-08-24, 2026-09-02 | C25: Based on normalized PKT coverage between the first and last PKT dates
A27: Inter-briefing gap register
A28: From Briefing | B28: To Briefing | C28: Gap Start UTC | D28: Gap End UTC | E28: Gap Minutes | F28: Gap Hours | G28: Approximate Missing 15M Runs | H28: Material Gap
A29: B001 | B29: B002 | C29: 46252.818 | D29: 46254.609 | E29: 2578.83 | F29: 42.98 | G29: 172 | H29: TRUE
A30: B002 | B30: B003 | C30: 46254.619 | D30: 46255.622 | E30: 1445.35 | F30: 24.09 | G30: 96 | H30: TRUE
A31: B003 | B31: B004 | C31: 46255.628 | D31: 46256.619 | E31: 1427 | F31: 23.78 | G31: 95 | H31: TRUE
A32: B004 | B32: B005 | C32: 46256.628 | D32: 46257.624 | E32: 1433 | F32: 23.88 | G32: 96 | H32: TRUE
A33: B005 | B33: B006 | C33: 46257.632 | D33: 46258.799 | E33: 1680 | F33: 28 | G33: 112 | H33: TRUE
A34: B006 | B34: B007 | C34: 46258.809 | D34: 46260.068 | E34: 1813 | F34: 30.22 | G34: 121 | H34: TRUE
A35: B007 | B35: B008 | C35: 46260.09 | D35: 46261.578 | E35: 2142 | F35: 35.7 | G35: 143 | H35: TRUE
A36: B008 | B36: B009 | C36: 46261.588 | D36: 46262.609 | E36: 1471 | F36: 24.52 | G36: 98 | H36: TRUE
A37: B009 | B37: B010 | C37: 46262.619 | D37: 46263.6 | E37: 1412 | F37: 23.53 | G37: 94 | H37: TRUE
A38: B010 | B38: B011 | C38: 46263.61 | D38: 46264.61 | E38: 1440 | F38: 24 | G38: 96 | H38: TRUE
A39: B011 | B39: B012 | C39: 46264.623 | D39: 46265.608 | E39: 1419 | F39: 23.65 | G39: 95 | H39: TRUE
A40: B012 | B40: B013 | C40: 46265.622 | D40: 46266.694 | E40: 1545 | F40: 25.75 | G40: 103 | H40: TRUE
A41: B013 | B41: B014 | C41: 46266.702 | D41: 46268.088 | E41: 1995 | F41: 33.25 | G41: 133 | H41: TRUE

Sheet Exclusions
A1: Exclusions
A2: Items excluded, deduplicated, or bounded out of the evidence register, with the reason and disposition retained.
A4: Item ID | B4: Item | C4: Type | D4: Reason | E4: Disposition
A5: EXC-001 | B5: pakistan-music-economy-meaning-man_1.html | C5: lack of Pakistan AI/digital-policy nexus | D5: Readable standalone essay about Pakistan’s music economy; not a monitoring brief and no material AI-policy or digital-infrastructure nexus. | E5: excluded from briefing dataset
A6: EXC-002 | B6: Strict-window no-change statements in B001–B014 | C6: repeated negative observation | D6: A no-change finding describes the bounded search window; it is not an underlying event and repetition is not corroboration. | E6: retained in coverage log, not event count
A7: EXC-003 | B7: Mutable PPRA headline counts | C7: unstable aggregate | D7: Counts moved and sometimes reset; without identifying underlying rows they do not establish a substantive procurement event. | E7: excluded from findings
A8: EXC-004 | B8: Generic PPRA rows | C8: out of scope | D8: Pneumatic items, generic security equipment, civil works, fire-hydrant evaluation and office relocation lack a material AI/digital-infrastructure nexus. | E8: excluded
A9: EXC-005 | B9: Guddu ST-16 / 747 MW work | C9: insufficient AI nexus | D9: General grid rehabilitation is not evidence of dedicated AI-compute energy supply. | E9: excluded
A10: EXC-006 | B10: ETPB data-centre evaluation EVL00000000515 | C10: outside reporting period | D10: Dated 4 May 2026; no in-span update was verified. | E10: excluded
A11: EXC-007 | B11: Date-only X-access claim | C11: unsupported/contradictory | D11: No primary PTA/Interior notice was located and the claim conflicted with earlier reporting. | E11: excluded pending primary evidence
A12: EXC-008 | B12: Daily Times under-16 article dated 3 September | C12: syndicated/repeated coverage | D12: Recycles the 31 August IHC proceeding and does not establish a new event. | E12: deduplicated into EVT-PLAT-20260831-IHC-U16
A13: EXC-009 | B13: Google directories and Pakistan-filtered jobs | C13: verification observation | D13: Directory contents and undated job listings help test claims but are not separate event milestones. | E13: used as evidence, not counted as events
A14: EXC-010 | B14: Google PID 21 August and MOIB 24 August releases | C14: duplicate official coverage | D14: Both describe the same framework MoU; the later ministry item is not independent corroboration. | E14: clustered into EVT-GOOG-20260821-MOU
A15: EXC-011 | B15: PISF 1 September press story | C15: repeated coverage | D15: Appears to repeat the 10/11 August Cabinet decision and published framework. | E15: retained as baseline context only
... A17: EXC-013 | B17: Files absent at 15-minute cadence | C17: missing evidence | D17: Missing briefings are not imputed and their absence is not evidence that no event occurred. | E17: coverage limitation

Sheet Briefing Units
A1: Briefing Units
A2: Normalized B001–B014 source provenance with exact filenames/subunits, UTC and PKT windows, timing issues, and source-file SHA-256.
A4: Briefing ID | B4: Source File | C4: Source Subunit | D4: Nominal Date | E4: Window Start UTC | F4: Window End UTC | G4: Window Start PKT | H4: Window End PKT | I4: Timestamp Basis | J4: Timing Issues | K4: Source File SHA-256
A5: B001 | B5: Pakistan AI Policy & Infrastructure Daily Brief — August 18, 2026.md | C5: Tab 1 | D5: 46252 | E5: 46252.808 | F5: 46252.818 | G5: 46253.017 | H5: 46253.026 | I5: explicit previous and research cutoffs | J5: Title date is UTC date; normalized PKT date is 2026-08-19. | K5: 45f7caa07f971e3fe5f24a7803eddc0aa4b4f6f2e08ece50d311bd5f1491f71a
A6: B002 | B6: Pakistan AI Policy & Infrastructure Daily Brief — August 18, 2026.md | C6: Tab 2 | D6: 46254 | E6: 46254.609 | F6: 46254.619 | G6: 46254.817 | H6: 46254.827 | I6: explicit PKT coverage window | J6: None identified. | K6: 45f7caa07f971e3fe5f24a7803eddc0aa4b4f6f2e08ece50d311bd5f1491f71a
A7: B003 | B7: Pakistan AI Policy & Infrastructure Daily Brief — August 18, 2026.md | C7: Tab 3 | D7: 46255 | E7: 46255.622 | F7: 46255.628 | G7: 46255.831 | H7: 46255.837 | I7: explicit approximate UTC and PKT window | J7: Window is explicitly approximate. | K7: 45f7caa07f971e3fe5f24a7803eddc0aa4b4f6f2e08ece50d311bd5f1491f71a
A8: B004 | B8: Pakistan_AI_Policy_Infrastructure_Daily_Brief_2026-08-22.docx | C8: whole document | D8: 46256 | E8: 46256.619 | F8: 46256.628 | G8: 46256.828 | H8: 46256.837 | I8: explicit approximate PKT window and UTC completion | J8: Window start is approximate. | K8: b0af106096750d5a4e9482d6d5db8ab45cbb392331b95199292a9636b5442cac
A9: B005 | B9: Pakistan_AI_Policy_Infrastructure_Daily_Brief_2026-08-23_2010PKT.docx | C9: whole document | D9: 46257 | E9: 46257.624 | F9: 46257.632 | G9: 46257.832 | H9: 46257.84 | I9: explicit previous cutoff plus stated 12-minute window and filename end time | J9: End time is reconstructed from stated duration and filename. | K9: 35f134b660569d76bb11abb2ed69531d2cdec50ba64a14d540e146e8ada3312b
A10: B006 | B10: Pakistan_AI_Policy_Infrastructure_Daily_Brief_2026-08-25_0025PKT.docx | C10: whole document | D10: 46259 | E10: 46258.799 | F10: 46258.809 | G10: 46259.007 | H10: 46259.017 | I10: explicit PKT comparison and research cutoffs | J10: UTC date is 2026-08-24 while nominal and PKT date are 2026-08-25. | K10: ad48d9540a3d628fa6db377c583f5fa6e9dffb87ead55fef2c403fcca6e86201
A11: B007 | B11: Pakistan_AI_Policy_Infrastructure_Daily_Brief_2026-08-26_0710PKT.docx | C11: whole document | D11: 46260 | E11: 46260.068 | F11: 46260.09 | G11: 46260.276 | H11: 46260.299 | I11: explicit PKT research window | J11: 32-minute interval materially exceeds the stated approximate 15-minute cadence. | K11: db82dd1e0bba6666d1826690596cf8b11a47b238b4f25a871457dd07639ba8f4
A12: B008 | B12: Pakistan_AI_Policy_Infrastructure_Daily_Brief_2026-08-27_1906PKT.docx | C12: whole document | D12: 46261 | E12: 46261.578 | F12: 46261.588 | G12: 46261.786 | H12: 46261.796 | I12: explicit approximate PKT coverage window | J12: Window end is approximate. | K12: e7913a1755df57d1686426dbb5b43829bc12e487f63f28bbf206779176dd38c0
A13: B009 | B13: Pakistan_AI_Policy_Infrastructure_Daily_Brief_2026-08-28_1952PKT.docx | C13: whole document | D13: 46262 | E13: 46262.609 | F13: 46262.619 | G13: 46262.817 | H13: 46262.828 | I13: explicit approximate UTC and PKT cutoffs | J13: Window end is approximate. | K13: 4cc02886b2335d8a3fa6370f2e291aeb51ce16760891090b6788054631b55b02
A14: B010 | B14: Pakistan_AI_Policy_Infrastructure_Daily_Brief_2026-08-29_1938PKT.docx | C14: whole document | D14: 46263 | E14: 46263.6 | F14: 46263.61 | G14: 46263.808 | H14: 46263.818 | I14: explicit PKT cutoffs | J14: Research cutoff is approximate in method text. | K14: b0da71141b840b8f8353b4e0da36467d93cf966d962465cd4ae4a7cca7eab03d
A15: B011 | B15: Pakistan_AI_Policy_Infrastructure_Daily_Brief_2026-08-30_1957PKT.docx | C15: whole document | D15: 46264 | E15: 46264.61 | F15: 46264.623 | G15: 46264.818 | H15: 46264.831 | I15: explicit approximate PKT and UTC cutoffs | J15: 19-minute interval exceeds the nominal cadence. | K15: e6dc40f617be9c3bd1b972a0ac9b48bfac31f1867e72d9d5b7f5c068703dd9dd
A16: B012 | B16: Pakistan_AI_Policy_Infrastructure_Daily_Brief_2026-08-31_1049ET.docx | C16: whole document | D16: 46265 | E16: 46265.608 | F16: 46265.622 | G16: 46265.817 | H16: 46265.83 | I16: explicit approximate UTC and PKT research window | J16: Filename says 1049ET, which converts to 14:49 UTC during EDT and falls inside, not at the end of, the stated window; ET is also DST-ambiguous. | K16: 39799a3296ff91e3e91a72db9724b0a5188d77d4bcb03fd8a380caee311000e6
... A18: B014 | B18: Pakistan_AI_Policy_Infrastructure_Daily_Brief_2026-09-02_2219ET.docx | C18: whole document | D18: 46267 | E18: 46268.088 | F18: 46268.098 | G18: 46268.296 | H18: 46268.306 | I18: explicit UTC and PKT research window; body identifies scheduled run as 22:19 EDT | J18: Filename nominal date is EDT; normalized UTC and PKT dates are 2026-09-03. Filename minute is scheduled time, two minutes before research cutoff. | K18: 7d2bc057f2d3e025074915e4e0d7ca194b13096465907a203981d127ee7ad822

Sheet Sources
A1: Sources
A2: S001–S111 primary and corroborating records with visible plain-text URLs, date fields, access status, and source-specific limitations.
A4: Source ID | B4: Publisher | C4: Document Title | D4: URL | E4: Source Type | F4: Publication Date | G4: Event Date | H4: Access Date UTC | I4: Availability | J4: Limitations
A5: S001 | B5: Ministry of IT and Telecommunication (MoITT) | C5: Policies register | D5: https://www.moitt.gov.pk/Policies | E5: official ministry register | F5: live | H5: 46268 | I5: opened and assessed | J5: Mutable register; current status captured at access time.
A6: S002 | B6: MoITT | C6: National Artificial Intelligence Policy | D6: https://www.moitt.gov.pk/SiteImage/Policies/National%20AI%20Policy.pdf | E6: official policy text | F6: 45869 | G6: 2025-07-30/31 | H6: 46268 | I6: opened and assessed | J6: MoITT register and Cabinet announcement differ by one day.
A7: S003 | B7: Radio Pakistan | C7: Federal Cabinet approves Hajj Policy 2026, Artificial Intelligence Policy 2025 | D7: https://www.radio.gov.pk/30-07-2025/federal-cabinet-approves-hajj-policy-2026-artificial-intelligence-policy-2025 | E7: official broadcaster | F7: 45868 | G7: 45868 | H7: 46268 | I7: opened and assessed | J7: Official summary, not the policy text.
A8: S004 | B8: Senate of Pakistan | C8: The Regulation of Artificial Intelligence Bill, 2024 — bill summary | D8: https://www.senate.gov.pk/en/billsummary.php?bid=1544 | E8: official parliamentary register | F8: live | G8: 45544 | H8: 46268 | I8: opened and assessed | J8: Register records disposition; not an enacted law.
A9: S005 | B9: MoITT | C9: Legislations register | D9: https://www.moitt.gov.pk/Legislations | E9: official ministry register | F9: live | H9: 46268 | I9: opened and assessed | J9: Mutable register; separates executive draft lineages.
A10: S006 | B10: National Assembly of Pakistan | C10: Debates / answer concerning data-protection legislation | D10: https://na.gov.pk/uploads/documents/6a1d62bdce349_708.pdf | E10: official parliamentary record | F10: 46156 | G10: 46156 | H10: 46268 | I10: opened and assessed | J10: Uses a heading referring to an Act while operative text still describes a bill/proposal.
A11: S007 | B11: Senate of Pakistan | C11: Private Members' Bills register | D11: https://senate.gov.pk/en/pbs.php?catid=1&cattitle=Bills&leftcatid=278&subcatid=276 | E11: official parliamentary register | F11: live | G11: 44970 | H11: 46268 | I11: opened and assessed | J11: Separate from MoITT executive drafts.
A12: S008 | B12: Senate of Pakistan | C12: Acts of Parliament register | D12: https://senate.gov.pk/en/acts.php | E12: official parliamentary register | F12: live | H12: 46268 | I12: opened and assessed | J12: Negative finding bounded to displayed register entries.
A13: S009 | B13: Pakistan Digital Authority (PDA) | C13: Pakistan Digital Authority to Oversee the Country's First National Data Governance Policy | D13: https://www.pda.gov.pk/press-details.php?id=data-governance-policy | E13: official authority release | F13: 46203 | G13: 46203 | H13: 46268 | I13: opened and assessed | J13: Describes a proposed draft and consultation.
A14: S010 | B14: PDA | C14: Consultations concluded on the National Data Governance Policy 2026 | D14: https://pda.gov.pk/press-details.php?id=pda-dgp-consultation | E14: official authority release | F14: 46239 | G14: 46239 | H14: 46268 | I14: opened and assessed | J14: 'Final stage' is process language, not proof of approval.
A15: S011 | B15: PDA | C15: From Fragmentation to Federation | D15: https://pda.gov.pk/press-details.php?id=from-fragmentation-to-federation | E15: official authority release | F15: 46255 | G15: 46255 | H15: 46268 | I15: opened and assessed | J15: Still describes the Data Governance Policy as a draft.
A16: S012 | B16: Ministry of Information and Broadcasting | C16: Cabinet approves Pakistan Information Security Framework 2026 | D16: https://www.moib.gov.pk/News/66315 | E16: official government release | F16: 46245 | G16: 2026-08-10/11 | H16: 46268 | I16: opened and assessed | J16: Summarizes Cabinet action; exact Cabinet decision date varies across reporting.
A17: S013 | B17: PKCERT | C17: GRC Policies — Pakistan Information Security Framework 2026 | D17: https://pkcert.gov.pk/grc-policies.asp | E17: official cybersecurity authority register | F17: live | H17: 46268 | I17: opened and assessed | J17: Links the framework and control suite; no standalone PISF SRO was located.
A18: S014 | B18: PKCERT | C18: Pakistan Information Security Framework 2026 — merged version | D18: https://pkcert.gov.pk/uploads/2026/03/PISF_Merged-Version.pdf | E18: official framework text | F18: 2026 | H18: 46268 | I18: opened and assessed | J18: Not itself an Act; enforceability outside expressly covered entities is not established.
A19: S015 | B19: Dawn | C19: Cabinet okays housing policy, cybersecurity framework | D19: https://www.dawn.com/news/2022051/cabinet-okays-housing-policy-cybersecurity-framework | E19: reputable news | F19: 46245 | G19: 46244 | H19: 46268 | I19: opened and assessed | J19: Secondary corroboration.
A20: S016 | B20: PDA / Digital Nation Pakistan | C20: Standards register | D20: https://standards.dnp.gov.pk/register.html | E20: official standards register | F20: live | H20: 46268 | I20: opened and assessed | J20: Four visible entries remain Pilot; two are working drafts.
A21: S017 | B21: PVARA | C21: Regulatory framework | D21: https://pvara.gov.pk/regulations | E21: official regulator register | F21: live | H21: 46268 | I21: opened and assessed | J21: Summary page contains a ten-year statement that is narrower in the operative text.
A22: S018 | B22: PVARA / Gazette of Pakistan | C22: Pakistan Virtual Asset Services Regulations, 2026 — S.R.O. 1419(I)/2026 | D22: https://pvara.gov.pk/documents/Pakistan%20Virtual%20Asset%20Services%20Regulations,%202026%20-%20Notified%2021%20August%202026.pdf | E22: official gazetted regulation | F22: 46255 | G22: 46255 | H22: 46268 | I22: opened and assessed | J22: Operative primary text.
A23: S019 | B23: PVARA / Gazette of Pakistan | C23: Pakistan Virtual Asset Services Activity Specific Regulations, 2026 — S.R.O. 1420(I)/2026 | D23: https://pvara.gov.pk/documents/Pakistan%20Virtual%20Asset%20Services%20Activity%20Specific%20Regulations,%202026%20-%20Notified%2021%20August%202026.pdf | E23: official gazetted regulation | F23: 46255 | G23: 46255 | H23: 46268 | I23: opened and assessed | J23: Operative primary text.
A24: S020 | B24: PVARA | C24: VASP licensing | D24: https://pvara.gov.pk/licensing | E24: official regulator guidance | F24: live | H24: 46268 | I24: opened and assessed | J24: Portal/guidance evidence; licence decisions must be checked separately.
A25: S021 | B25: Radio Pakistan | C25: Pakistan introduces regulatory system for digital economy | D25: https://radio.gov.pk/22-08-2026/pakistan-introduces-transparent-regulatory-system-for-digital-economy | E25: official broadcaster | F25: 46256 | G25: 46255 | H25: 46268 | I25: opened and assessed | J25: Official summary, not operative text.
A26: S022 | B26: PKCERT | C26: Advisories index | D26: https://pkcert.gov.pk/advisories.asp | E26: official cybersecurity authority register | F26: live | H26: 46268 | I26: opened and assessed | J26: Index lacks displayed publication dates.
A27: S023 | B27: PKCERT | C27: Advisory 16 — Malware Targeting Synchronized Passkeys on Compromised Windows Systems | D27: https://pkcert.gov.pk/advisory/26/16.pdf | E27: official advisory | F27: 46258 | G27: 46258 | H27: 46268 | I27: opened and assessed | J27: Date supported by identifier and PDF metadata; exact release time unavailable.
A28: S024 | B28: PKCERT | C28: Advisory 17 — Adobe Acrobat Chrome Extension Vulnerability Exposing WhatsApp Web Sessions | D28: https://pkcert.gov.pk/advisory/26/17.pdf | E28: official advisory | F28: 46258 | G28: 46258 | H28: 46268 | I28: opened and assessed | J28: Date supported by identifier and PDF metadata; exact release time unavailable.
A29: S025 | B29: Press Information Department (PID) | C29: MoITT to introduce fresh bill to expedite legislative process on PTRA | D29: https://pid.gov.pk/site/press_detail/33741 | E29: official government release | F29: 46262 | G29: 46262 | H29: 46268 | I29: opened and assessed | J29: Fresh bill is stated intent, not a verified introduction.
A30: S026 | B30: Senate of Pakistan | C30: Government Bills transmitted by the National Assembly | D30: https://www.senate.gov.pk/en/gbna.php?catid=186&cattitle=Bills&leftcatid=279&subcatid=276 | E30: official parliamentary register | F30: live | G30: 46262 | H30: 46268 | I30: opened and assessed | J30: Records withdrawal; no successor text was visible at cutoff.
A31: S027 | B31: Khyber Pakhtunkhwa Assembly | C31: The Khyber Pakhtunkhwa Promotion of Digital Payments Bill, 2026 | D31: https://www.pakp.gov.pk/bill/the-khyber-pakhtunkhwa-promotion-of-digital-payments-bill-2026/ | E31: official provincial parliamentary register | F31: live | G31: 46118 | H31: 46268 | I31: opened and assessed | J31: Current status says referred to Standing Committee No. 10.
A32: S028 | B32: Express Tribune | C32: K-P Assembly approves digital payments bill | D32: https://tribune.com.pk/story/2625229/k-p-assembly-approves-digital-payments-bill | E32: reputable news | F32: 46256 | G32: 46255 | H32: 46268 | I32: opened and assessed | J32: Headline/passsage claim conflicts with current official tracker and article body says introduced.
A33: S029 | B33: DGIPR Khyber Pakhtunkhwa | C33: Standing committee considers workplace-harassment amendments | D33: https://dgipr.kp.gov.pk/sc-27-8-26/ | E33: official provincial release | F33: 46261 | G33: 46261 | H33: 46268 | I33: opened and assessed | J33: Urdu release; describes committee action, not enactment.
A34: S030 | B34: SECP | C34: SECP website / circular register | D34: https://www.secp.gov.pk/ | E34: official regulator site | F34: live | H34: 46268 | I34: opened and assessed | J34: Initial discovery source only; the direct instrument and official document page are S101-S102.
A35: S031 | B35: Super Law Services | C35: SuperNews 28-8-2026 | D35: https://superlawpk.com/archives/12908 | E35: specialist commentary/index | F35: 46262 | G35: 46261 | H35: 46268 | I35: opened and assessed | J35: Initial discovery corroboration only; not a substitute for the SECP instrument at S101-S102.
A36: S032 | B36: HUM News | C36: Punjab Assembly passes resolution to ban social media accounts for under-16s | D36: https://humenglish.com/latest/punjab-assembly-passes-resolution-to-ban-social-media-accounts-for-under-16s/ | E36: news report | F36: 46266 | G36: 46266 | H36: 46268 | I36: opened and assessed | J36: Official resolution text was not located; resolution is not legislation.
A37: S033 | B37: Dawn | C37: IHC seeks replies on under-16 social-media age verification | D37: https://www.dawn.com/news/2026379 | E37: reputable news | F37: 46265 | G37: 46265 | H37: 46268 | I37: opened and assessed | J37: Authenticated court order not located.
A38: S034 | B38: Business Recorder | C38: Social media age verification: IHC directs authorities to submit reply | D38: https://www.brecorder.com/news/40437291/social-media-age-verification-ihc-direct-authorities-to-submit-reply | E38: reputable news | F38: 46266 | G38: 46265 | H38: 46268 | I38: opened and assessed | J38: Secondary corroboration; not the order.
A39: S035 | B39: Associated Press of Pakistan (APP) | C39: NADRA, FBISE sign agreement to integrate student registration, educational certificates system | D39: https://www.app.com.pk/national/nadra-fbise-sign-agreement-to-integrate-student-registration-educational-certificates-system/ | E39: official news agency | F39: 46266 | G39: 46266 | H39: 46268 | I39: opened and assessed | J39: Agreement text and production evidence unavailable.
A40: S036 | B40: PPRA | C40: National AI Hubs tender TS0000010287E | D40: https://epms.ppra.gov.pk/public/tenders/tender-details/TS0000010287E | E40: official procurement record | F40: 46252 | G40: 46265 | H40: 46268 | I40: opened and assessed | J40: Current closing field and corrigendum history conflict; no evaluation or award visible.
A41: S037 | B41: EPADS | C41: Establishment of National AI Hubs procurement 71677 | D41: https://epads.gov.pk/opportunities/federal/procurements/71677 | E41: official procurement record | F41: 46252 | G41: 46265 | H41: 46268 | I41: opened and assessed | J41: Tender-stage record.
A42: S038 | B42: PPRA | C42: MoITT AI capacity-building tender TS0000006913E | D42: https://epms.ppra.gov.pk/public/tenders/tender-details/TS0000006913E | E42: official procurement record | F42: 46165 | G42: 46253 | H42: 46268 | I42: opened and assessed | J42: Evaluation/lowest-bidder stage is not award.
A43: S039 | B43: PPRA | C43: Evaluation results register — MoITT AI training | D43: https://epms.ppra.gov.pk/public/evaluations?page=7 | E43: official procurement register | F43: 46253 | G43: 46253 | H43: 46268 | I43: opened and assessed | J43: Mutable paginated register.
A44: S040 | B44: PPRA | C44: NAVTTC AI-enabled services tender TS0000010237E | D44: https://epms.ppra.gov.pk/public/tenders/tender-details/TS0000010237E | E44: official procurement record | F44: 2026 | G44: 2026-08-21/28 | H44: 46268 | I44: opened and assessed | J44: Procurement stage only.
A45: S041 | B45: PPRA | C45: NAVTTC technical evaluation EVL00000002896 | D45: https://epms.ppra.gov.pk/public/evaluations?page=1 | E45: official procurement register | F45: 46255 | G45: 46255 | H45: 46268 | I45: opened and assessed | J45: Six bids; mutable paginated register.
A46: S042 | B46: PPRA | C46: NAVTTC final evaluation EVL00000003006 | D46: https://epms.ppra.gov.pk/public/evaluations?page=4 | E46: official procurement register | F46: 46262 | G46: 46262 | H46: 46268 | I46: opened and assessed | J46: Lowest evaluated bidder is not award/contract.
A47: S043 | B47: PPRA | C47: PTA AI-powered DIRBS tender TS0000011207E | D47: https://epms.ppra.gov.pk/public/tenders/tender-details/TS0000011207E | E47: official procurement record | F47: 46244 | G47: 46261 | H47: 46268 | I47: opened and assessed | J47: No evaluation, award, system design, or safeguards visible.
A48: S044 | B48: EPADS | C48: PTA annual procurement-plan record for DIRBS | D48: https://epads.gov.pk/federal/annual-plan/procurement/2473/7564/2026-27 | E48: official procurement-plan record | F48: 2026 | H48: 46268 | I48: opened and assessed | J48: Plan/tender metadata conflict; do not conflate stages.
A49: S045 | B49: PPRA | C49: NADRA NDW racks, containment systems and PDUs tender TS0000010535E | D49: https://epms.ppra.gov.pk/public/tenders/tender-details/TS0000010535E | E49: official procurement record | F49: 46232 | G49: 46254 | H49: 46268 | I49: opened and assessed | J49: No evaluation, award, delivery, or commissioning visible.
A50: S046 | B50: PPRA | C50: NADRA branch switches and management licences tender TS0000010591E | D50: https://epms.ppra.gov.pk/public/tenders/tender-details/TS0000010591E | E50: official procurement record | F50: 2026 | G50: 46254 | H50: 46268 | I50: opened and assessed | J50: No evaluation, award, delivery, or commissioning visible.
A51: S047 | B51: UN Global Marketplace / WHO | C51: RFP EM/PAK — GIS-Enabled Digital EPI Microplanning and NEIR Integration in Balochistan | D51: https://www.ungm.org/Public/Notice/310156 | E51: international institution procurement | F51: 2026-08-24 in B006 capture; current page displays 2026-08-28 | G51: 2026-08-27/2026-09-06 | H51: 46268 | I51: opened and assessed | J51: Mutable record: B006 transcribed ‘Published 24 Aug 2026’; the current page displays ‘Published 28-Aug-2026’. The page also retains superseded deadlines; latest displayed deadline is 6 September 2026 11:00 PKT.
A52: S048 | B52: Jazz | C52: Jazz becomes first operator to reach 1,000 5G sites | D52: https://jazz.com.pk/media-center/detail/jazz-becomes-first-operator-to-reach-1000-5g-sites | E52: direct company release | F52: 46261 | G52: 46261 | H52: 46268 | I52: opened and assessed | J52: Company-reported footprint; no independent QoS/capex audit.
A53: S049 | B53: Jazz | C53: Jazz secures 190 MHz spectrum to accelerate Pakistan's 5G future | D53: https://jazz.com.pk/media-center/detail/jazz-secures-190-mhz-spectrum-to-accelerate-pakistans-5g-future | E53: direct company release | F53: 2026 | H53: 46268 | I53: opened and assessed | J53: Direct company context for spectrum and investment commitment.
A54: S050 | B54: PPRA | C54: FAB spectrum-monitoring contract PCN-3884318406 | D54: https://epms.ppra.gov.pk/public/contracts/contract-details/PCN-3884318406 | E54: official procurement contract record | F54: 46259 | G54: 46255 | H54: 46268 | I54: opened and assessed | J54: Contract does not prove installation, commissioning, or acceptance.
A55: S051 | B55: PID | C55: Jam Kamal Khan pushes sovereign cloud and AI-powered trade ecosystem | D55: https://pid.gov.pk/site/press_detail/33671 | E55: official government release | F55: 46255 | G55: 46255 | H55: 46268 | I55: opened and assessed | J55: Meeting/discussion only; contains no 8.5 MW claim.
A56: S052 | B56: Radio Pakistan | C56: PM, Field Marshal inaugurate Sky47 Karakoram-01 Data Centre | D56: https://www.radio.gov.pk/24-07-2026/pm-field-marshal-inaugurate-sky47-karakorum-01-data-centre | E56: official broadcaster | F56: 46227 | G56: 46227 | H56: 46268 | I56: opened and assessed | J56: Canonical Radio Pakistan URL replacing the retired new.radio.gov.pk staging host; still only supports the inauguration baseline, not certified IT load, GPU inventory or operational utilisation.
A57: S053 | B57: Data Center Dynamics | C57: Pakistani operator Sky47 inaugurates 8.5MW data center in Islamabad | D57: https://www.datacenterdynamics.com/en/news/pakistani-operator-sky47-inaugurates-85mw-data-center-in-islamabad/ | E57: specialist industry news | F57: 46232 | G57: 46227 | H57: 46268 | I57: opened and assessed | J57: 8.5 MW is facility-level reporting; IT load/utilisation not independently established.
A58: S054 | B58: Mari Energies / Pakistan Stock Exchange | C58: Material information concerning data-centre venture | D58: https://dps.psx.com.pk/download/document/254563.pdf | E58: company exchange disclosure | F58: 2026 | H58: 46268 | I58: opened and assessed | J58: Contains plans/targets that should not be treated as commissioning evidence.
A59: S055 | B59: Dawn / Resecurity | C59: Resecurity and Sky47 partner to enable sovereign cybersecurity and AI infrastructure in Pakistan | D59: https://www.dawn.com/news/2025965/resecurity-and-sky47-partner-to-enable-sovereign-cybersecurity-and-ai-infrastructure-in-pakistan | E59: advertorial / direct company claim | F59: 46263 | G59: signing date unstated; announcement 2026-08-27 | H59: 46268 | I59: opened and assessed | J59: Explicit advertorial; forward-looking partnership language and no deployment proof.
A60: S056 | B60: MoITT | C60: Pakistan's National Semiconductor Cluster Framework now complete as NED joins SERC | D60: https://www.moitt.gov.pk/NewsDetail/MTJmOTg2OGQtOTNlYi00MDZjLTk0MDktNGRiMmQzMTEzYTdm | E60: official ministry release | F60: 46263 | G60: 46263 | H60: 46268 | I60: opened and assessed | J60: Contract itself, budget, lab specification and delivery evidence unavailable.
A61: S057 | B61: NED University | C61: Events — INSPIRE / PSEB semiconductor cluster | D61: https://www.neduet.edu.pk/content/events | E61: university publication | F61: live | G61: 2026 | H61: 46268 | I61: opened and assessed | J61: Sparse supporting entry; no contract text.
A62: S058 | B62: APP | C62: Maryam delivers address at Big Data Industry Expo | D62: https://www.app.com.pk/punjab/maryam-delivers-thought-provoking-address-at-big-data-industry-expo/ | E62: official news agency | F62: 46262 | G62: 46262 | H62: 46268 | I62: opened and assessed | J62: Relays Punjab government claims; no architecture, legal instrument, or acceptance record.
A63: S059 | B63: DGIPR Khyber Pakhtunkhwa | C63: KP digital-government delivery update | D63: https://dgipr.kp.gov.pk/stit-28-8-26/ | E63: official provincial release | F63: 46262 | G63: 46261 | H63: 46268 | I63: opened and assessed | J63: Government self-report; independent service-volume/outcome evidence absent.
A64: S060 | B64: Business Recorder | C64: Punjab, Huawei agree to expand AI, digital cooperation | D64: https://www.brecorder.com/news/40436971/punjab-huawei-agree-to-expand-ai-digital-cooperation | E64: reputable news | F64: 46263 | G64: 46262 | H64: 46268 | I64: opened and assessed | J64: No primary signed instrument, financing, site, or capacity source located.
A65: S061 | B65: APP | C65: Alibaba Cloud shows interest in Punjab's IT sector | D65: https://www.app.com.pk/punjab/alibaba-cloud-shows-keen-interest-in-punjabs-it-sector-cm-maryam-invites-chinese-ai-collaboration/ | E65: official news agency | F65: 46264 | G65: 46264 | H65: 46268 | I65: opened and assessed | J65: Reports discussion/potential partnership, not implementation.
A66: S062 | B66: Radio Pakistan | C66: AI being integrated into governance system in Punjab: CM | D66: https://radio.gov.pk/30-08-2026/ai-being-integrated-into-governance-system-in-punjab-cm | E66: official broadcaster | F66: 46264 | G66: 46264 | H66: 46268 | I66: opened and assessed | J66: Government handout; no signed text or delivery evidence.
A67: S063 | B67: DGIPR Khyber Pakhtunkhwa | C67: World Bank delegation meets KP government on IT, digital infrastructure and energy initiatives | D67: https://dgipr.kp.gov.pk/world-bank-delegation-meets-khyber-pakhtunkhwa-government-to-discuss-it-digital-infrastructure-and-energy-initiatives/ | E67: official provincial release | F67: 46265 | G67: 46262 | H67: 46268 | I67: opened and assessed | J67: Page says meeting occurred Friday; publication and event dates differ.
A68: S064 | B68: APP | C68: Shaza meets Saudi Minister of Communications and Information Technology | D68: https://www.app.com.pk/national/shaza-meets-saudi-minister-of-communications-and-information-technology/ | E68: official news agency | F68: 46266 | G68: 46266 | H68: 46268 | I68: opened and assessed | J68: No instrument, project, financing, or timetable disclosed.
A69: S065 | B69: Arab News Pakistan | C69: Minister says Pakistan will share digital infrastructure with emerging economies | D69: https://www.arabnews.pk/pakistan/minister-tells-saudi-expo-pakistan-will-share-digital-infrastructure-free-with-emerging-economies-3000008 | E69: reputable international news | F69: 46266 | G69: 46266 | H69: 46268 | I69: opened and assessed | J69: Ministerial intention; code, licence, readiness, recipients and safeguards unavailable.
A70: S066 | B70: Punjab Auqaf and Religious Affairs Department | C70: AI-based digital monitoring system at model shrines | D70: https://auqaf.punjab.gov.pk/node/835 | E70: official provincial release | F70: 46267 | G70: 46267 | H70: 46268 | I70: opened and assessed | J70: Operational claim is authority-reported; vendor, biometric scope and assurance evidence absent.
A71: S067 | B71: APP Video | C71: Punjab minister announces PBTE digitisation and AI courses | D71: https://vid.app.com.pk/vid/2026/09/%D8%B5%D9%88%D8%A8%D8%A7%D8%A6%DB%8C-%D9%88%D8%B2%DB%8C%D8%B1-%D8%B5%D9%86%D8%B9%D8%AA-%D9%88-%D8%AA%D8%AC%D8%A7%D8%B1%D8%AA-%DA%86%D9%88%D8%AF%DA%BE%D8%B1%DB%8C-%D8%B4%D8%A7%D9%81%D8%B9-%D8%AD-41/ | E71: official news agency video | F71: 46267 | G71: 46267 | H71: 46268 | I71: 404 on 2026-09-03 audit; retained as provenance/archive-only | J71: The APP video mixed PBTE digitisation claims with a separate PTUT course announcement and lacks institutional artefacts proving course delivery, system operation or acceptance.
A72: S068 | B72: Planning Commission of Pakistan | C72: CDWP considers Emerging Technologies Data Centre and National AI Ecosystem Development Program | D72: https://www.pc.gov.pk/web/press/get_press/1702 | E72: official planning release | F72: 46198 | G72: 2026-06-18 / 2026-06-25 (official conflict) | H72: 46268 | I72: opened and assessed | J72: In-principle/recommendation stage; not ECNEC approval, release, award, construction or operation.
A73: S069 | B73: PPRA | C73: Sovereign National AI Infrastructure RFP TS0000010170E | D73: https://epms.ppra.gov.pk/public/tenders/tender-details/TS0000010170E | E73: official procurement record | F73: 46227 | G73: 46286 | H73: 46268 | I73: opened and assessed | J73: Open/pre-award; page's weekday label for 21 September is erroneous.
A74: S070 | B74: Punjab Information Technology Board | C74: Tender notices | D74: https://pitb.gov.pk/tendernotices | E74: official provincial procurement register | F74: live | H74: 46268 | I74: opened and assessed | J74: Mutable page; Government AI Cloud and later GPU identities/dates need document-level reconciliation.
A75: S071 | B75: PITB | C75: Bid document DC-11 — GPU servers | D75: https://pitb.gov.pk/system/files/BD_DC-11_Corrigen-Published.pdf | E75: official procurement document | F75: 2026 | G75: 46205 | H75: 46268 | I75: opened and assessed | J75: Closed baseline; quantities must not be transferred to other GPU tenders.
A76: S072 | B76: PITB | C76: Bid document ITOPS-23 — AI-enabled data-centre package | D76: https://pitb.gov.pk/system/files/BD_ITOPS_23_Corrigen_Published.pdf | E76: official procurement document | F76: 2026 | G76: 46204 | H76: 46268 | I76: opened and assessed | J76: Closed baseline; no award or accepted delivery located.
A77: S073 | B77: Dubai International Financial Centre | C77: Dubai FinTech Summit expands globally with Pakistan Digital Authority | D77: https://www.difc.com/whats-on/news/difcs-dubai-fintech-summit-expands-globally-with-pakistan-digital-authority | E77: direct institution release | F77: 46076 | H77: 46268 | I77: opened and assessed | J77: Advance announcement does not prove later summit outcomes.
A78: S074 | B78: PID | C78: Prime Minister meets Google delegation and unveils plaque | D78: https://pid.gov.pk/site/press_detail/33638 | E78: official government release | F78: 46252 | G78: 46252 | H78: 46268 | I78: opened and assessed | J78: Ceremony occurred at Prime Minister House; no office street address, occupancy or staffing evidence.
A79: S075 | B79: PDA | C79: Google opens office in Pakistan | D79: https://pda.gov.pk/press-details.php?id=google-opens-office-in-pakistan | E79: official authority release | F79: 46266 | G79: 46252 | H79: 46268 | I79: opened and assessed | J79: Retrospective government claim; no office address or operational particulars.
A80: S076 | B80: Dawn | C80: Google announces local office as prime minister unveils plaque | D80: https://www.dawn.com/news/2023681 | E80: reputable news | F80: 46252 | G80: 46252 | H80: 46268 | I80: opened and assessed | J80: Relays Google/company statement but provides no premises evidence.
A81: S077 | B81: PID | C81: Government of Pakistan–Google framework MoU | D81: https://pid.gov.pk/site/press_detail/33684 | E81: official government release | F81: 46255 | G81: 46255 | H81: 46268 | I81: opened and assessed | J81: Instrument and implementation workplan were not published.
A82: S078 | B82: Ministry of Information and Broadcasting | C82: Google framework MoU and digital-skills programmes | D82: https://www.moib.gov.pk/News/66341 | E82: official government release | F82: 46258 | G82: 46255 | H82: 46268 | I82: opened and assessed | J82: Later release describing same agreement; not independent corroboration.
A83: S079 | B83: PID | C83: Government claims concerning Google programmes in Pakistan | D83: https://pid.gov.pk/site/press_detail/33645 | E83: official government release | F83: 46253 | G83: 46253 | H83: 46268 | I83: opened and assessed | J83: Programme numbers are government claims, not independently audited outcomes.
A84: S080 | B84: Google Ads Help | C84: Taxes in your country — Google Pakistan (Private) Limited | D84: https://support.google.com/google-ads/answer/2375370?hl=en-GB | E84: direct company operational guidance | F84: live | G84: 2026-08-01/2026-10-01 | H84: 46268 | I84: opened and assessed | J84: Verifies a limited commercial/tax counterparty role, not a physical office.
A85: S081 | B85: Google | C85: Office locations | D85: https://about.google/company-info/locations/ | E85: direct company directory | F85: live | H85: 46268 | I85: opened and assessed | J85: No Pakistan match at cutoff; absence does not prove no local presence.
A86: S082 | B86: Google Cloud | C86: Global locations — regions and zones | D86: https://cloud.google.com/about/locations | E86: direct company directory | F86: live | H86: 46268 | I86: opened and assessed | J86: No Pakistan region at cutoff.
A87: S083 | B87: Google Data Centers | C87: Locations | D87: https://datacenters.google/locations/ | E87: direct company directory | F87: live | H87: 46268 | I87: opened and assessed | J87: No Pakistan owned-data-centre location at cutoff.
A88: S084 | B88: Google Careers | C88: Pakistan-filtered jobs | D88: https://www.google.com/about/careers/applications/jobs/results?location=Pakistan | E88: direct company jobs directory | F88: live | H88: 46268 | I88: opened and assessed | J88: Three matches at cutoff, two explicit Karachi; postings lack a shared event timestamp.
A89: S085 | B89: National Assembly of Pakistan | C89: Acts register | D89: https://www.na.gov.pk/en/acts.php | E89: official parliamentary register | F89: live | H89: 46268 | I89: opened and assessed | J89: No in-scope horizontal personal-data Act visible at cutoff.
A90: S086 | B90: Sky47 | C90: Sky47 and Resecurity sign a Memorandum of Understanding | D90: https://www.linkedin.com/posts/sky47limited_sky47-resecurity-cybersecurity-activity-7498665122295517184-fA11 | E90: direct company announcement | F90: 46261 | G90: signing date unstated | H90: 46268 | I90: opened and assessed | J90: First-party LinkedIn post marked Edited; exact announcement timestamp inferred from the native activity identifier.
A91: S087 | B91: C-Suite Exchange | C91: Sky47 and Resecurity sign MoU to strengthen cybersecurity collaboration | D91: https://c-suite.exchange/sky47-and-resecurity-sign-mou-to-strengthen-cybersecurity-collaboration/ | E91: trade publication | F91: 46261 | G91: signing date unstated | H91: 46268 | I91: opened and assessed | J91: Corroborates the public announcement; independence from company-provided material is unclear.
A92: S088 | B92: Press Information Department | C92: Pakistan's National Semiconductor Cluster Framework now complete as NED joins SERC | D92: https://pid.gov.pk/site/press_detail/33749 | E92: official government release | F92: 46263 | G92: 46263 | H92: 46268 | I92: opened and assessed | J92: Confirms contract/designation but does not publish the contract, its value, or a commencement certificate.
A93: S089 | B93: Pakistan Software Export Board | C93: RFP for three Semiconductor Education and Research Clusters | D93: https://techdestination.com/wp-content/uploads/2025/09/Request-for-Proposal-NSHRDP-SERC-Procurement-2.51.pdf | E93: official procurement document | F93: 2025 | H93: 46268 | I93: opened and assessed | J93: Procurement framework establishes downstream inspection and commencement steps; it is not proof those steps occurred.
A94: S090 | B94: Press Information Department | C94: National Semiconductor Human Resource Development Program budget and targets | D94: https://pid.gov.pk/site/press_detail/32338 | E94: official government release | F94: 2026 | H94: 46268 | I94: opened and assessed | J94: PKR 4.844 billion is the whole NSHRDP budget, not the NED contract value.
A95: S091 | B95: Express Tribune | C95: Citizen facilitation centres planned | D95: https://tribune.com.pk/story/2626183/citizen-facilitation-centres-planned?amp=1 | E95: reputable news | F95: 46262 | G95: 46261 | H95: 46268 | I95: opened and assessed | J95: Appears derived from the same provincial handout and is not independent operational corroboration.
A96: S092 | B96: Associated Press of Pakistan | C96: Punjab CM, Huawei agree to expand AI, digital cooperation | D96: https://www.app.com.pk/punjab/punjab-cm-huawei-agree-to-expand-ai-digital-cooperation/ | E96: official news agency | F96: 46262 | G96: 46262 | H96: 46268 | I96: opened and assessed | J96: Government-side account; no Huawei release, signed instrument, financing, site, or capacity specification was found.
A97: S093 | B97: Express Tribune | C97: Chinese firm shows interest in Punjab IT sector | D97: https://tribune.com.pk/story/2626664/chinese-firm-shows-interest-in-punjab-it-sector?amp=1 | E97: reputable news | F97: 46265 | G97: 46264 | H97: 46268 | I97: opened and assessed | J97: Appears handout-derived; supports meeting chronology, not an independent project commitment.
A98: S094 | B98: Radio Pakistan | C98: Pakistan, Alibaba Group ink agreements to boost digital-economy cooperation | D98: https://radio.gov.pk/24-05-2026/pakistan-alibaba-group-ink-agreements-to-boost-digital-economy-cooperation | E98: official broadcaster | F98: 46166 | G98: 46166 | H98: 46268 | I98: opened and assessed | J98: Earlier national agreements are context and must not be conflated with the 30 August Punjab meeting.
A99: S095 | B99: Business Recorder | C99: KP, World Bank team discuss IT, digital infrastructure and energy initiatives | D99: https://www.brecorder.com/news/40437177/advisor-cs-kp-world-bank-team-discuss-it-digital-infrastructure-list-6 | E99: reputable news | F99: 46265 | G99: 46262 | H99: 46268 | I99: opened and assessed | J99: Repeats the provincial account; no World Bank release or financing decision was located.
A100: S096 | B100: Saudi National Cybersecurity Authority | C100: Saudi Arabia and Pakistan sign cybersecurity MoU | D100: https://nca.gov.sa/ar/news/2581/ | E100: official foreign-government release | F100: 46266 | G100: 46266 | H100: 46268 | I100: opened and assessed | J100: Confirms the signed cybersecurity MoU; full instrument, term and workplan were not published.
A101: S097 | B101: Radio Pakistan | C101: Pakistan, Saudi Arabia sign MoU in area of cybersecurity | D101: https://www.radio.gov.pk/02-09-2026/pakistan-saudi-arabia-sign-mou-in-area-of-cybersecurity | E101: official broadcaster | F101: 46267 | G101: 46266 | H101: 46268 | I101: opened and assessed | J101: Cross-party governmental corroboration; no full instrument.
...

Sheet Watchlist
A1: Watchlist
A2: Future dates and triggers that require human re-verification; listing does not imply completion or occurrence.
A4: Watch ID | B4: Date Or Trigger | C4: Topic | D4: What To Verify | E4: Source ID | F4: Source URL
A5: W001 | B5: 46270 | C5: PVARA transition deadline | D5: Complete applications, NOCs/licences, published reasons, transitional enforcement and cloud/cross-border implementation. | E5: S020 | F5: https://pvara.gov.pk/licensing
A6: W002 | B6: 2026-09-06 11:00 PKT | C6: WHO Balochistan GIS/NEIR RFP | D6: Final deadline, bids, award, hosting, access, retention, ethics and production acceptance. | E6: S047 | F6: https://www.ungm.org/Public/Notice/310156
A7: W003 | B7: 46275 | C7: NTC power/resilience procurements | D7: Conflicting battery deadline, awards, installation, failover testing and acceptance. | E7: S110 | F7: https://epms.ppra.gov.pk/public/tenders/tender-details/TS0000011042E
A8: W004 | B8: 2026-09-21 15:00 PKT | C8: Sovereign National AI Infrastructure RFP | D8: Bid opening, evaluation, award, capacity, site, energy/cooling, access model, security and acceptance. | E8: S069 | F8: https://epms.ppra.gov.pk/public/tenders/tender-details/TS0000010170E
A9: W005 | B9: 46288 | C9: State Life Karachi core switches | D9: Evaluation, award, delivery and commissioning. | E9: S111 | F9: https://epms.ppra.gov.pk/public/tenders/tender-details/TS0000012358E
A10: W006 | B10: 2026-09-30 target | C10: Sky47 Port Qasim expansion | D10: Actual commissioning, certification, MW/IT load, customers, GPUs, power/cooling and acceptance. | E10: S054 | F10: https://dps.psx.com.pk/download/document/254563.pdf
A11: W007 | B11: 46296 | C11: Google Pakistan invoicing transition | D11: Invoices issued by local entity for eligible accounts, tax treatment, product scope and any premises/employment disclosures. | E11: S080 | F11: https://support.google.com/google-ads/answer/2375370?hl=en-GB
A12: W008 | B12: Next official register update | C12: National Data Governance Policy and personal-data legislation | D12: Final text, approval/notification, introduced bill, passage, assent, Gazette and commencement. | E12: S001 | F12: https://www.moitt.gov.pk/Policies
A13: W009 | B13: Next procurement update | C13: National AI Hubs, MoITT training, NAVTTC AI services and PTA DIRBS | D13: Opening/evaluation/award/contract/deployment/acceptance; do not infer completion from lowest-bidder or closing status. | E13: S041 | F13: https://epms.ppra.gov.pk/public/evaluations?page=1
A14: W010 | B14: Next official/company disclosure | C14: Google physical presence | D14: Street address, office type, occupancy, employing entity, staffing, mandate, investment, local processing/hosting, Cloud region or owned data centre. | E14: S081 | F14: https://about.google/company-info/locations/
A15: W011 | B15: Next court/parliament update | C15: Under-16 platform proposals | D15: IHC authenticated order/filings, official Punjab resolution, any bill or PTA instrument, age-assurance design and privacy/redress safeguards. | E15: S033 | F15: https://www.dawn.com/news/2026379
A16: W012 | B16: Next agency publication | C16: NADRA–FBISE and Auqaf monitoring | D16: Legal basis, data maps, access/logging, retention, biometrics, security, human review, correction and audit. | E16: S035 | F16: https://www.app.com.pk/national/nadra-fbise-sign-agreement-to-integrate-student-registration-educational-certificates-system/
A17: W013 | B17: Next PITB tender-register update | C17: PITB DC-02 GPU server procurement | D17: Direct tender identity, governing deadline, quantities, budget, evaluation, award, delivery and acceptance. | E17: S070 | F17: https://pitb.gov.pk/tendernotices
A18: W014 | B18: Next primary-source discovery | C18: Gomal University data centre and RDA portal claims | D18: Direct institutional records, technical scope, contract or award, operating status, safeguards and acceptance evidence.

Sheet File Inventory
A1: File Inventory
A2: Every received top-level file, with format, size, timestamps, SHA-256, readability, apparent coverage, and inclusion decision.
A4: Source File | B4: Format | C4: Detected Type | D4: Bytes | E4: Filesystem Birthtime | F4: Filesystem Mtime | G4: SHA-256 | H4: Readable | I4: Container Status | J4: Internal Title | K4: Internal Creator | L4: Internal Created | M4: Internal Modified | N4: Apparent Briefing Units | O4: Apparent Coverage UTC | P4: Inclusion Decision | Q4: Notes
A5: Pakistan AI Policy & Infrastructure Daily Brief — August 18, 2026.md | B5: md | C5: Unicode text, UTF-8 text, with very long lines (485) | D5: 28165 | E5: 46268.124 | F5: 46268.124 | G5: 45f7caa07f971e3fe5f24a7803eddc0aa4b4f6f2e08ece50d311bd5f1491f71a | H5: TRUE | I5: not applicable | N5: 3 | O5: 2026-08-18T19:24:00Z to 2026-08-21T15:05:00Z | P5: include as briefing evidence | Q5: Single Markdown download containing three labeled briefing tabs.
A6: Pakistan_AI_Policy_Infrastructure_Daily_Brief_2026-08-22.docx | B6: docx | C6: Microsoft OOXML | D6: 46701 | E6: 46268.119 | F6: 46268.119 | G6: b0af106096750d5a4e9482d6d5db8ab45cbb392331b95199292a9636b5442cac | H6: TRUE | I6: valid OOXML ZIP | J6: Pakistan AI Policy & Infrastructure Daily Brief — 22 August 2026 | K6: Pakistan AI Policy Monitor | L6: 41631.969 | M6: 41631.969 | N6: 1 | O6: 2026-08-22T14:52:00Z to 2026-08-22T15:05:00Z | P6: include as briefing evidence | Q6: OOXML core creation/modification timestamps are template defaults and not usable as briefing timestamps.
A7: Pakistan_AI_Policy_Infrastructure_Daily_Brief_2026-08-23_2010PKT.docx | B7: docx | C7: Microsoft OOXML | D7: 45691 | E7: 46268.119 | F7: 46268.119 | G7: 35f134b660569d76bb11abb2ed69531d2cdec50ba64a14d540e146e8ada3312b | H7: TRUE | I7: valid OOXML ZIP | J7: Pakistan AI Policy & Infrastructure Daily Brief — 23 August 2026 | K7: Pakistan AI Policy Monitor | L7: 41631.969 | M7: 41631.969 | N7: 1 | O7: 2026-08-23T14:58:00Z to 2026-08-23T15:10:00Z | P7: include as briefing evidence | Q7: OOXML core creation/modification timestamps are template defaults and not usable as briefing timestamps.
A8: Pakistan_AI_Policy_Infrastructure_Daily_Brief_2026-08-25_0025PKT.docx | B8: docx | C8: Microsoft OOXML | D8: 47772 | E8: 46268.12 | F8: 46268.12 | G8: ad48d9540a3d628fa6db377c583f5fa6e9dffb87ead55fef2c403fcca6e86201 | H8: TRUE | I8: valid OOXML ZIP | J8: Pakistan AI Policy & Infrastructure Daily Brief — 25 August 2026 | K8: Pakistan AI Policy Monitor | L8: 41631.969 | M8: 41631.969 | N8: 1 | O8: 2026-08-24T19:10:00Z to 2026-08-24T19:25:00Z | P8: include as briefing evidence | Q8: OOXML core creation/modification timestamps are template defaults and not usable as briefing timestamps.
A9: Pakistan_AI_Policy_Infrastructure_Daily_Brief_2026-08-26_0710PKT.docx | B9: docx | C9: Microsoft OOXML | D9: 45938 | E9: 46268.12 | F9: 46268.12 | G9: db82dd1e0bba6666d1826690596cf8b11a47b238b4f25a871457dd07639ba8f4 | H9: TRUE | I9: valid OOXML ZIP | J9: Pakistan AI Policy & Infrastructure Daily Brief — 26 August 2026 | K9: Pakistan AI Policy Monitor | L9: 41631.969 | M9: 41631.969 | N9: 1 | O9: 2026-08-26T01:38:00Z to 2026-08-26T02:10:00Z | P9: include as briefing evidence | Q9: OOXML core creation/modification timestamps are template defaults and not usable as briefing timestamps.
A10: Pakistan_AI_Policy_Infrastructure_Daily_Brief_2026-08-27_1906PKT.docx | B10: docx | C10: Microsoft OOXML | D10: 45788 | E10: 46268.12 | F10: 46268.12 | G10: e7913a1755df57d1686426dbb5b43829bc12e487f63f28bbf206779176dd38c0 | H10: TRUE | I10: valid OOXML ZIP | J10: Pakistan AI Policy & Infrastructure Daily Brief - August 27, 2026 | K10: Pakistan AI Policy Monitor | L10: 41631.969 | M10: 41631.969 | N10: 1 | O10: 2026-08-27T13:52:00Z to 2026-08-27T14:06:00Z | P10: include as briefing evidence | Q10: OOXML core creation/modification timestamps are template defaults and not usable as briefing timestamps.
A11: Pakistan_AI_Policy_Infrastructure_Daily_Brief_2026-08-28_1952PKT.docx | B11: docx | C11: Microsoft OOXML | D11: 47590 | E11: 46268.12 | F11: 46268.12 | G11: 4cc02886b2335d8a3fa6370f2e291aeb51ce16760891090b6788054631b55b02 | H11: TRUE | I11: valid OOXML ZIP | J11: Pakistan AI Policy & Infrastructure Daily Brief — 28 August 2026 | K11: Pakistan AI Policy Monitor | L11: 41631.969 | M11: 41631.969 | N11: 1 | O11: 2026-08-28T14:37:00Z to 2026-08-28T14:52:00Z | P11: include as briefing evidence | Q11: OOXML core creation/modification timestamps are template defaults and not usable as briefing timestamps.
A12: Pakistan_AI_Policy_Infrastructure_Daily_Brief_2026-08-29_1938PKT.docx | B12: docx | C12: Microsoft OOXML | D12: 49996 | E12: 46268.121 | F12: 46268.121 | G12: b0da71141b840b8f8353b4e0da36467d93cf966d962465cd4ae4a7cca7eab03d | H12: TRUE | I12: valid OOXML ZIP | J12: Pakistan AI Policy & Infrastructure Daily Brief — 29 August 2026 | K12: Pakistan AI Policy Monitor | L12: 41631.969 | M12: 41631.969 | N12: 1 | O12: 2026-08-29T14:24:00Z to 2026-08-29T14:38:00Z | P12: include as briefing evidence | Q12: OOXML core creation/modification timestamps are template defaults and not usable as briefing timestamps.
A13: Pakistan_AI_Policy_Infrastructure_Daily_Brief_2026-08-30_1957PKT.docx | B13: docx | C13: Microsoft OOXML | D13: 45578 | E13: 46268.121 | F13: 46268.121 | G13: e6dc40f617be9c3bd1b972a0ac9b48bfac31f1867e72d9d5b7f5c068703dd9dd | H13: TRUE | I13: valid OOXML ZIP | J13: Pakistan AI Policy & Infrastructure Daily Brief — 30 August 2026 | K13: Pakistan AI Policy Monitor | L13: 41631.969 | M13: 41631.969 | N13: 1 | O13: 2026-08-30T14:38:00Z to 2026-08-30T14:57:00Z | P13: include as briefing evidence | Q13: OOXML core creation/modification timestamps are template defaults and not usable as briefing timestamps.
A14: Pakistan_AI_Policy_Infrastructure_Daily_Brief_2026-08-31_1049ET.docx | B14: docx | C14: Microsoft OOXML | D14: 46515 | E14: 46268.121 | F14: 46268.121 | G14: 39799a3296ff91e3e91a72db9724b0a5188d77d4bcb03fd8a380caee311000e6 | H14: TRUE | I14: valid OOXML ZIP | J14: Pakistan AI Policy & Infrastructure Daily Brief — 31 August 2026 | K14: Pakistan AI Policy Monitor | L14: 41631.969 | M14: 41631.969 | N14: 1 | O14: 2026-08-31T14:36:00Z to 2026-08-31T14:55:00Z | P14: include as briefing evidence | Q14: OOXML core creation/modification timestamps are template defaults and not usable as briefing timestamps.
A15: Pakistan_AI_Policy_Infrastructure_Daily_Brief_2026-09-01_1249ET.docx | B15: docx | C15: Microsoft OOXML | D15: 48098 | E15: 46268.121 | F15: 46268.121 | G15: 8ef5556ab900fbe7ca9e12743ca2ad819d719453e9031958c1e116d0c3441339 | H15: TRUE | I15: valid OOXML ZIP | J15: Pakistan AI Policy & Infrastructure Daily Brief — 1 September 2026 | K15: Pakistan AI Policy Monitor | L15: 41631.969 | M15: 41631.969 | N15: 1 | O15: 2026-09-01T16:40:00Z to 2026-09-01T16:51:00Z | P15: include as briefing evidence | Q15: OOXML core creation/modification timestamps are template defaults and not usable as briefing timestamps.
A16: Pakistan_AI_Policy_Infrastructure_Daily_Brief_2026-09-02_2219ET.docx | B16: docx | C16: Microsoft OOXML | D16: 47855 | E16: 46268.121 | F16: 46268.121 | G16: 7d2bc057f2d3e025074915e4e0d7ca194b13096465907a203981d127ee7ad822 | H16: TRUE | I16: valid OOXML ZIP | J16: Pakistan AI Policy & Infrastructure Daily Brief - 2 September 2026 | K16: Pakistan AI Policy Monitor | L16: 41631.969 | M16: 41631.969 | N16: 1 | O16: 2026-09-03T02:06:00Z to 2026-09-03T02:21:00Z | P16: include as briefing evidence | Q16: OOXML core creation/modification timestamps are template defaults and not usable as briefing timestamps.
A17: pakistan-music-economy-meaning-man_1.html | B17: html | C17: HTML document text, Unicode text, UTF-8 text, with very long lines (711) | D17: 39655 | E17: 46263.875 | F17: 46263.875 | G17: 5f6ae05bed6396e2b16f37ea3929e2fd10c714f02ae1834ae75d3546fa8eb961 | H17: TRUE | I17: not applicable | N17: 0 | P17: exclude from briefing dataset | Q17: Readable standalone article about Pakistan's music economy; excluded for lack of an AI-policy/digital-infrastructure nexus.

Sheet Methodology
A1: Methodology
A2: Extraction, normalization, event clustering, verification, conflict treatment, and refresh protocol.
A4: Reproducibility chain
A5: Step | B5: Stage | C5: Reproducible action
A6: 1 | B6: Inventory | C6: Hash and inspect all 13 received top-level files; confirm readability, type, and container status.
A7: 2 | B7: Normalize | C7: Extract 14 briefing units, retain source filenames/subunits, and normalize explicit UTC/PKT windows.
A8: 3 | B8: Cluster | C8: Merge repeated briefing mentions into one underlying event while retaining every briefing reference.
A9: 4 | B9: Verify | C9: Prioritize primary operative records, record access dates, and use independent reporting only as corroboration or context.
A10: 5 | B10: Classify | C10: Separate facts, attributed source claims, analysis, implications, confidence, unresolved issues, and lifecycle status.
A11: 6 | B11: Reconcile | C11: Retain conflicting versions explicitly; do not overwrite captured dates with mutable live-page values.
A12: 7 | B12: Refresh | C12: Re-open every source URL, reconfirm lifecycle status, record a new cutoff, and rerun the audit/build/verification chain.
A15: Methodological rules
A16: Comprehensive boundary | B16: Comprehensive with respect to the supplied files and documented verification searches; not proof that every relevant public event was captured.
A17: Timestamp authority | B17: Use explicit internal UTC/PKT windows as authoritative. Filename dates/times and filesystem timestamps are discovery metadata only; reconstructed endpoints remain approximate.
A18: Negative findings | B18: Do not infer no change from missing intervals. State only what is supported by the supplied files and documented verification searches.
A19: Lifecycle precision | B19: Distinguish proposal, consultation, recommendation, approval, notification, award, signing, delivery, commissioning, and operation.
A20: Source hierarchy | B20: Primary law/gazette/regulator/procurement record → official institution/company → independent reporting → supplied briefing as discovery provenance.
A21: Corroboration | B21: Later releases about the same underlying event do not create independent corroboration; briefing repetition is provenance, not a second source.
A22: Conflict treatment | B22: Preserve each dated version and its access context. WHO S047 retains 24 August in B006 versus 28 August on the current mutable page.
A23: Google presence | B23: Keep legal/tax counterparty evidence separate from physical-office evidence, staffing, operational control, and service availability.
A26: Confidence rubric
A27: Class | B27: Rule
A28: High | B28: Direct, accessible primary record supports the event and lifecycle status; material contradictions are resolved or explicitly bounded.
A29: Medium | B29: Core event is supported, but the operative instrument, implementation evidence, independent corroboration or important particulars are missing.
A30: Low | B30: Only an indirect, secondary, inaccessible or contradictory record supports the claim; no provision-level or implementation conclusion is drawn.
A32: Lifecycle taxonomy
A33: IN_SPAN_DEVELOPMENT | B33: Distinct development whose authoritative date or verification discovery falls within the observed period.
A34: BASELINE_CARRY_IN | B34: Earlier instrument or event retained because it governs interpretation of the observed period.
A35: MONITORED_NO_CHANGE | B35: Monitored baseline for which a supported status check found no material change.
A36: CORRECTION | B36: Documented correction to a prior assertion or lifecycle classification.
A37: CONTRADICTED_OR_UNRESOLVED | B37: Material source conflict, missing operative text, or unresolved identity/status question.
A38: FUTURE_WATCH | B38: Forward trigger that requires a later evidence check; not an accomplished event.
A39: EXCLUDED_OUT_OF_SCOPE | B39: Item excluded from the evidence register but documented in the exclusion log.
A42: Category taxonomy
A43: AI_GOVERNANCE | E43: DATA_PROTECTION_GOVERNANCE
A44: CYBERSECURITY | E44: DIGITAL_IDENTITY_DPI
A45: PLATFORM_TELECOM | E45: COMPUTE_CLOUD_DATACENTRE
A46: CONNECTIVITY_ENERGY_RESILIENCE | E46: PROCUREMENT_PROGRAM_DELIVERY
A47: FUNDING_INVESTMENT_PARTNERSHIP | E47: WORKFORCE_RESEARCH_EDUCATION
A48: GOOGLE_CORPORATE_PRESENCE
